Workbook
Name Slicer_Delivery_Status: #N/A
Name Slicer_Month: #N/A
Name Slicer_Payment_Method: #N/A
Name Slicer_Payment_Method1: #N/A
Name Slicer_Product_Category: #N/A
Name Slicer_Region: #N/A

Sheet AmazonSales_RawData
A1: Order ID | B1: Order Date | C1: Delivery Date | D1: Cancel Date | E1: Customer ID | F1: Product ID | G1: Region | H1: Sale Price/Unit | I1: Quantity | J1: Total Amount | K1: Payment Method | L1: Delivery Status | M1: Fulfillment Partner
A2: ORD0001 | B2: 12/31/2023 | D2: 1/2/2024 | E2: CUST021 | F2: PROD012 | G2: North | H2: 44 | I2: 1 | J2: 44 | K2: Apple Pay | L2: Cancelled | M2: DHL
A3: ORD0002 | B3: 2/22/2023 | C3: 2/24/2023 | E3: CUST029 | F3: PROD018 | G3: East | H3: 96 | I3: 4 | J3: 384 | K3: Credit Card | L3: Delivered | M3: DHL
A4: ORD0003 | B4: 10/11/2023 | E4: CUST021 | F4: PROD013 | G4: South | H4: 194 | I4: 4 | J4: 776 | K4: Credit Card | L4: In Transit | M4: USPS
A5: ORD0004 | B5: 5/5/2023 | D5: 5/11/2023 | E5: CUST044 | F5: PROD013 | G5: North | H5: 196 | I5: 3 | J5: 588 | K5: PayPal | L5: Cancelled | M5: UPS
A6: ORD0005 | B6: 2/2/2023 | C6: 2/5/2023 | E6: CUST027 | F6: PROD010 | G6: North | H6: 59 | I6: 1 | J6: 59 | K6: PayPal | L6: Delivered | M6: Amazon Logistics
A7: ORD0006 | B7: 11/1/2023 | D7: 11/2/2023 | E7: CUST009 | F7: PROD010 | G7: North | H7: 58 | I7: 4 | J7: 232 | K7: Amazon Pay | L7: Cancelled | M7: DHL
A8: ORD0007 | B8: 8/14/2023 | D8: 8/18/2023 | E8: CUST042 | F8: PROD020 | G8: Central | H8: 105 | I8: 3 | J8: 315 | K8: Debit Card | L8: Cancelled | M8: DHL
A9: ORD0008 | B9: 4/1/2023 | D9: 4/6/2023 | E9: CUST019 | F9: PROD021 | G9: West | H9: 37 | I9: 5 | J9: 185 | K9: PayPal | L9: Cancelled | M9: DHL
A10: ORD0009 | B10: 7/21/2023 | E10: CUST013 | F10: PROD019 | G10: Central | H10: 44 | I10: 2 | J10: 88 | K10: Credit Card | L10: In Transit | M10: Amazon Logistics
A11: ORD0010 | B11: 12/29/2023 | E11: CUST019 | F11: PROD003 | G11: South | H11: 141 | I11: 4 | J11: 564 | K11: Debit Card | L11: In Transit | M11: DHL
A12: ORD0011 | B12: 5/4/2023 | D12: 5/8/2023 | E12: CUST046 | F12: PROD014 | G12: South | H12: 249 | I12: 1 | J12: 249 | K12: Amazon Pay | L12: Cancelled | M12: USPS
A13: ORD0012 | B13: 7/25/2023 | E13: CUST045 | F13: PROD014 | G13: Central | H13: 247 | I13: 3 | J13: 741 | K13: Amazon Pay | L13: In Transit | M13: FedEx
A14: ORD0013 | B14: 2/25/2023 | D14: 2/28/2023 | E14: CUST023 | F14: PROD006 | G14: Central | H14: 96 | I14: 1 | J14: 96 | K14: Apple Pay | L14: Cancelled | M14: Amazon Logistics
A15: ORD0014 | B15: 2/24/2023 | D15: 2/25/2023 | E15: CUST033 | F15: PROD017 | G15: West | H15: 74 | I15: 5 | J15: 370 | K15: Apple Pay | L15: Cancelled | M15: Amazon Logistics
A16: ORD0015 | B16: 8/26/2023 | D16: 9/2/2023 | E16: CUST033 | F16: PROD005 | G16: South | H16: 27 | I16: 1 | J16: 27 | K16: Credit Card | L16: Cancelled | M16: Amazon Logistics
A17: ORD0016 | B17: 2/13/2023 | E17: CUST047 | F17: PROD005 | G17: South | H17: 27 | I17: 3 | J17: 81 | K17: Debit Card | L17: In Transit | M17: Amazon Logistics
A18: ORD0017 | B18: 6/28/2023 | C18: 7/1/2023 | E18: CUST045 | F18: PROD015 | G18: East | H18: 21 | I18: 3 | J18: 63 | K18: Credit Card | L18: Delivered | M18: DHL
A19: ORD0018 | B19: 11/28/2023 | E19: CUST011 | F19: PROD008 | G19: West | H19: 70 | I19: 5 | J19: 350 | K19: PayPal | L19: In Transit | M19: Amazon Logistics
A20: ORD0019 | B20: 8/25/2023 | E20: CUST041 | F20: PROD006 | G20: South | H20: 94 | I20: 4 | J20: 376 | K20: Credit Card | L20: In Transit | M20: USPS
A21: ORD0020 | B21: 4/12/2023 | E21: CUST025 | F21: PROD001 | G21: North | H21: 813 | I21: 2 | J21: 1626 | K21: Credit Card | L21: In Transit | M21: FedEx
A22: ORD0021 | B22: 10/2/2023 | E22: CUST013 | F22: PROD015 | G22: Central | H22: 21 | I22: 4 | J22: 84 | K22: PayPal | L22: In Transit | M22: Amazon Logistics
A23: ORD0022 | B23: 11/9/2023 | E23: CUST023 | F23: PROD012 | G23: West | H23: 46 | I23: 5 | J23: 230 | K23: PayPal | L23: In Transit | M23: USPS
A24: ORD0023 | B24: 2/13/2023 | D24: 2/14/2023 | E24: CUST016 | F24: PROD010 | G24: West | H24: 58 | I24: 3 | J24: 174 | K24: Amazon Pay | L24: Cancelled | M24: Amazon Logistics
A25: ORD0024 | B25: 11/2/2023 | C25: 11/5/2023 | E25: CUST028 | F25: PROD006 | G25: West | H25: 96 | I25: 5 | J25: 480 | K25: Amazon Pay | L25: Delivered | M25: Amazon Logistics
A26: ORD0025 | B26: 5/28/2023 | C26: 5/30/2023 | E26: CUST040 | F26: PROD002 | G26: South | H26: 43 | I26: 1 | J26: 43 | K26: Debit Card | L26: Delivered | M26: Amazon Logistics
A27: ORD0026 | B27: 10/15/2023 | C27: 10/21/2023 | E27: CUST027 | F27: PROD022 | G27: South | H27: 64 | I27: 4 | J27: 256 | K27: Debit Card | L27: Delivered | M27: USPS
A28: ORD0027 | B28: 1/16/2023 | E28: CUST018 | F28: PROD008 | G28: South | H28: 70 | I28: 2 | J28: 140 | K28: Amazon Pay | L28: In Transit | M28: Amazon Logistics
A29: ORD0028 | B29: 10/9/2023 | E29: CUST018 | F29: PROD018 | G29: Central | H29: 97 | I29: 3 | J29: 291 | K29: Credit Card | L29: In Transit | M29: Amazon Logistics
A30: ORD0029 | B30: 10/7/2023 | D30: 10/10/2023 | E30: CUST007 | F30: PROD021 | G30: East | H30: 37 | I30: 3 | J30: 111 | K30: Apple Pay | L30: Cancelled | M30: DHL
A31: ORD0030 | B31: 2/14/2023 | E31: CUST008 | F31: PROD008 | G31: North | H31: 69 | I31: 5 | J31: 345 | K31: Amazon Pay | L31: In Transit | M31: Amazon Logistics
A32: ORD0031 | B32: 3/26/2023 | E32: CUST014 | F32: PROD002 | G32: North | H32: 42 | I32: 5 | J32: 210 | K32: Amazon Pay | L32: In Transit | M32: UPS
A33: ORD0032 | B33: 6/15/2023 | D33: 6/22/2023 | E33: CUST037 | F33: PROD009 | G33: East | H33: 11 | I33: 5 | J33: 55 | K33: Debit Card | L33: Cancelled | M33: FedEx
A34: ORD0033 | B34: 5/22/2023 | C34: 5/23/2023 | E34: CUST016 | F34: PROD005 | G34: South | H34: 27 | I34: 2 | J34: 54 | K34: Apple Pay | L34: Delivered | M34: USPS
A35: ORD0034 | B35: 11/20/2023 | E35: CUST025 | F35: PROD015 | G35: South | H35: 21 | I35: 1 | J35: 21 | K35: Amazon Pay | L35: In Transit | M35: DHL
A36: ORD0035 | B36: 12/22/2023 | C36: 12/26/2023 | E36: CUST032 | F36: PROD011 | G36: South | H36: 172 | I36: 1 | J36: 172 | K36: PayPal | L36: Delivered | M36: USPS
A37: ORD0036 | B37: 7/23/2023 | E37: CUST014 | F37: PROD016 | G37: North | H37: 212 | I37: 3 | J37: 636 | K37: Amazon Pay | L37: In Transit | M37: UPS
A38: ORD0037 | B38: 10/17/2023 | C38: 10/22/2023 | E38: CUST044 | F38: PROD002 | G38: East | H38: 41 | I38: 4 | J38: 164 | K38: Credit Card | L38: Delivered | M38: Amazon Logistics
A39: ORD0038 | B39: 8/22/2023 | D39: 8/24/2023 | E39: CUST028 | F39: PROD007 | G39: North | H39: 32 | I39: 2 | J39: 64 | K39: Debit Card | L39: Cancelled | M39: FedEx
A40: ORD0039 | B40: 12/2/2023 | E40: CUST024 | F40: PROD022 | G40: East | H40: 66 | I40: 2 | J40: 132 | K40: Apple Pay | L40: In Transit | M40: DHL
A41: ORD0040 | B41: 12/25/2023 | E41: CUST006 | F41: PROD004 | G41: East | H41: 62 | I41: 4 | J41: 248 | K41: Debit Card | L41: In Transit | M41: UPS
A42: ORD0041 | B42: 9/23/2023 | C42: 9/30/2023 | E42: CUST001 | F42: PROD011 | G42: West | H42: 173 | I42: 4 | J42: 692 | K42: Apple Pay | L42: Delivered | M42: UPS
A43: ORD0042 | B43: 7/16/2023 | C43: 7/18/2023 | E43: CUST007 | F43: PROD004 | G43: West | H43: 63 | I43: 3 | J43: 189 | K43: Apple Pay | L43: Delivered | M43: UPS
A44: ORD0043 | B44: 2/5/2023 | D44: 2/11/2023 | E44: CUST040 | F44: PROD021 | G44: West | H44: 36 | I44: 3 | J44: 108 | K44: Debit Card | L44: Cancelled | M44: USPS
A45: ORD0044 | B45: 12/18/2023 | D45: 12/23/2023 | E45: CUST006 | F45: PROD004 | G45: Central | H45: 62 | I45: 1 | J45: 62 | K45: Apple Pay | L45: Cancelled | M45: Amazon Logistics
A46: ORD0045 | B46: 6/11/2023 | D46: 6/14/2023 | E46: CUST042 | F46: PROD003 | G46: Central | H46: 137 | I46: 5 | J46: 685 | K46: Amazon Pay | L46: Cancelled | M46: FedEx
A47: ORD0046 | B47: 12/4/2023 | C47: 12/8/2023 | E47: CUST039 | F47: PROD017 | G47: North | H47: 73 | I47: 4 | J47: 292 | K47: Credit Card | L47: Delivered | M47: Amazon Logistics
A48: ORD0047 | B48: 7/17/2023 | C48: 7/19/2023 | E48: CUST041 | F48: PROD020 | G48: North | H48: 104 | I48: 1 | J48: 104 | K48: PayPal | L48: Delivered | M48: Amazon Logistics
A49: ORD0048 | B49: 10/19/2023 | C49: 10/24/2023 | E49: CUST044 | F49: PROD006 | G49: East | H49: 97 | I49: 1 | J49: 97 | K49: Amazon Pay | L49: Delivered | M49: FedEx
A50: ORD0049 | B50: 5/15/2023 | E50: CUST026 | F50: PROD017 | G50: South | H50: 73 | I50: 5 | J50: 365 | K50: Apple Pay | L50: In Transit | M50: Amazon Logistics
A51: ORD0050 | B51: 2/12/2023 | C51: 2/19/2023 | E51: CUST040 | F51: PROD005 | G51: East | H51: 27 | I51: 3 | J51: 81 | K51: Amazon Pay | L51: Delivered | M51: UPS
A52: ORD0051 | B52: 10/2/2023 | E52: CUST041 | F52: PROD021 | G52: North | H52: 37 | I52: 1 | J52: 37 | K52: Apple Pay | L52: In Transit | M52: UPS
A53: ORD0052 | B53: 1/30/2023 | C53: 2/1/2023 | E53: CUST008 | F53: PROD015 | G53: North | H53: 22 | I53: 1 | J53: 22 | K53: Debit Card | L53: Delivered | M53: FedEx
A54: ORD0053 | B54: 12/29/2023 | C54: 1/1/2024 | E54: CUST011 | F54: PROD016 | G54: Central | H54: 218 | I54: 5 | J54: 1090 | K54: PayPal | L54: Delivered | M54: DHL
A55: ORD0054 | B55: 3/6/2023 | D55: 3/13/2023 | E55: CUST018 | F55: PROD004 | G55: North | H55: 64 | I55: 1 | J55: 64 | K55: Apple Pay | L55: Cancelled | M55: USPS
A56: ORD0055 | B56: 2/2/2023 | C56: 2/6/2023 | E56: CUST037 | F56: PROD021 | G56: Central | H56: 36 | I56: 4 | J56: 144 | K56: PayPal | L56: Delivered | M56: Amazon Logistics
A57: ORD0056 | B57: 10/18/2023 | C57: 10/21/2023 | E57: CUST017 | F57: PROD004 | G57: West | H57: 65 | I57: 1 | J57: 65 | K57: Amazon Pay | L57: Delivered | M57: FedEx
A58: ORD0057 | B58: 1/7/2023 | C58: 1/9/2023 | E58: CUST025 | F58: PROD005 | G58: Central | H58: 26 | I58: 1 | J58: 26 | K58: Apple Pay | L58: Delivered | M58: DHL
A59: ORD0058 | B59: 5/8/2023 | E59: CUST021 | F59: PROD009 | G59: North | H59: 11 | I59: 5 | J59: 55 | K59: Credit Card | L59: In Transit | M59: FedEx
A60: ORD0059 | B60: 4/2/2023 | D60: 4/5/2023 | E60: CUST003 | F60: PROD013 | G60: North | H60: 195 | I60: 4 | J60: 780 | K60: PayPal | L60: Cancelled | M60: FedEx
A61: ORD0060 | B61: 10/11/2023 | D61: 10/12/2023 | E61: CUST019 | F61: PROD019 | G61: West | H61: 44 | I61: 5 | J61: 220 | K61: Apple Pay | L61: Cancelled | M61: USPS
A62: ORD0061 | B62: 9/10/2023 | E62: CUST035 | F62: PROD008 | G62: East | H62: 69 | I62: 4 | J62: 276 | K62: Debit Card | L62: In Transit | M62: DHL
A63: ORD0062 | B63: 11/22/2023 | C63: 11/29/2023 | E63: CUST022 | F63: PROD001 | G63: North | H63: 815 | I63: 4 | J63: 3260 | K63: Credit Card | L63: Delivered | M63: USPS
A64: ORD0063 | B64: 5/2/2023 | E64: CUST004 | F64: PROD005 | G64: East | H64: 27 | I64: 1 | J64: 27 | K64: Debit Card | L64: In Transit | M64: Amazon Logistics
A65: ORD0064 | B65: 12/25/2023 | C65: 12/29/2023 | E65: CUST048 | F65: PROD003 | G65: West | H65: 139 | I65: 5 | J65: 695 | K65: Apple Pay | L65: Delivered | M65: USPS
A66: ORD0065 | B66: 10/18/2023 | D66: 10/20/2023 | E66: CUST009 | F66: PROD008 | G66: South | H66: 69 | I66: 3 | J66: 207 | K66: PayPal | L66: Cancelled | M66: Amazon Logistics
A67: ORD0066 | B67: 5/20/2023 | D67: 5/21/2023 | E67: CUST009 | F67: PROD019 | G67: West | H67: 42 | I67: 1 | J67: 42 | K67: Apple Pay | L67: Cancelled | M67: DHL
A68: ORD0067 | B68: 7/28/2023 | C68: 7/30/2023 | E68: CUST050 | F68: PROD007 | G68: North | H68: 31 | I68: 4 | J68: 124 | K68: Credit Card | L68: Delivered | M68: UPS
A69: ORD0068 | B69: 12/18/2023 | E69: CUST045 | F69: PROD020 | G69: West | H69: 104 | I69: 3 | J69: 312 | K69: Credit Card | L69: In Transit | M69: UPS
A70: ORD0069 | B70: 7/2/2023 | D70: 7/7/2023 | E70: CUST044 | F70: PROD010 | G70: East | H70: 58 | I70: 2 | J70: 116 | K70: Apple Pay | L70: Cancelled | M70: USPS
A71: ORD0070 | B71: 10/9/2023 | D71: 10/10/2023 | E71: CUST009 | F71: PROD004 | G71: West | H71: 62 | I71: 2 | J71: 124 | K71: Debit Card | L71: Cancelled | M71: DHL
A72: ORD0071 | B72: 12/18/2023 | C72: 12/25/2023 | E72: CUST006 | F72: PROD019 | G72: East | H72: 43 | I72: 1 | J72: 43 | K72: Credit Card | L72: Delivered | M72: Amazon Logistics
A73: ORD0072 | B73: 3/7/2023 | E73: CUST022 | F73: PROD004 | G73: East | H73: 62 | I73: 4 | J73: 248 | K73: Debit Card | L73: In Transit | M73: Amazon Logistics
A74: ORD0073 | B74: 7/22/2023 | D74: 7/25/2023 | E74: CUST028 | F74: PROD006 | G74: North | H74: 95 | I74: 2 | J74: 190 | K74: PayPal | L74: Cancelled | M74: UPS
A75: ORD0074 | B75: 1/18/2023 | C75: 1/24/2023 | E75: CUST016 | F75: PROD021 | G75: Central | H75: 36 | I75: 4 | J75: 144 | K75: Apple Pay | L75: Delivered | M75: FedEx
A76: ORD0075 | B76: 5/24/2023 | E76: CUST042 | F76: PROD017 | G76: East | H76: 73 | I76: 5 | J76: 365 | K76: Apple Pay | L76: In Transit | M76: DHL
A77: ORD0076 | B77: 9/3/2023 | C77: 9/9/2023 | E77: CUST023 | F77: PROD019 | G77: North | H77: 43 | I77: 4 | J77: 172 | K77: Debit Card | L77: Delivered | M77: DHL
A78: ORD0077 | B78: 11/2/2023 | C78: 11/4/2023 | E78: CUST004 | F78: PROD016 | G78: West | H78: 214 | I78: 5 | J78: 1070 | K78: Debit Card | L78: Delivered | M78: UPS
A79: ORD0078 | B79: 12/3/2023 | D79: 12/6/2023 | E79: CUST048 | F79: PROD002 | G79: Central | H79: 42 | I79: 2 | J79: 84 | K79: Apple Pay | L79: Cancelled | M79: UPS
A80: ORD0079 | B80: 4/1/2023 | E80: CUST048 | F80: PROD012 | G80: North | H80: 46 | I80: 1 | J80: 46 | K80: Amazon Pay | L80: In Transit | M80: UPS
A81: ORD0080 | B81: 10/16/2023 | C81: 10/19/2023 | E81: CUST032 | F81: PROD018 | G81: East | H81: 95 | I81: 4 | J81: 380 | K81: Credit Card | L81: Delivered | M81: UPS
A82: ORD0081 | B82: 11/5/2023 | E82: CUST001 | F82: PROD011 | G82: West | H82: 174 | I82: 2 | J82: 348 | K82: PayPal | L82: In Transit | M82: UPS
A83: ORD0082 | B83: 6/15/2023 | D83: 6/18/2023 | E83: CUST046 | F83: PROD005 | G83: North | H83: 27 | I83: 5 | J83: 135 | K83: Credit Card | L83: Cancelled | M83: Amazon Logistics
A84: ORD0083 | B84: 10/28/2023 | C84: 10/30/2023 | E84: CUST021 | F84: PROD005 | G84: South | H84: 27 | I84: 4 | J84: 108 | K84: PayPal | L84: Delivered | M84: USPS
A85: ORD0084 | B85: 12/22/2023 | E85: CUST015 | F85: PROD022 | G85: South | H85: 65 | I85: 2 | J85: 130 | K85: PayPal | L85: In Transit | M85: DHL
A86: ORD0085 | B86: 3/7/2023 | E86: CUST045 | F86: PROD019 | G86: East | H86: 43 | I86: 5 | J86: 215 | K86: Debit Card | L86: In Transit | M86: DHL
A87: ORD0086 | B87: 11/10/2023 | E87: CUST007 | F87: PROD016 | G87: West | H87: 210 | I87: 1 | J87: 210 | K87: PayPal | L87: In Transit | M87: UPS
A88: ORD0087 | B88: 11/22/2023 | E88: CUST043 | F88: PROD021 | G88: South | H88: 37 | I88: 3 | J88: 111 | K88: Credit Card | L88: In Transit | M88: UPS
A89: ORD0088 | B89: 5/8/2023 | E89: CUST007 | F89: PROD001 | G89: South | H89: 788 | I89: 4 | J89: 3152 | K89: Debit Card | L89: In Transit | M89: Amazon Logistics
A90: ORD0089 | B90: 7/13/2023 | E90: CUST007 | F90: PROD016 | G90: West | H90: 217 | I90: 5 | J90: 1085 | K90: Debit Card | L90: In Transit | M90: FedEx
A91: ORD0090 | B91: 1/18/2023 | E91: CUST007 | F91: PROD003 | G91: West | H91: 138 | I91: 4 | J91: 552 | K91: Credit Card | L91: In Transit | M91: FedEx
A92: ORD0091 | B92: 6/23/2023 | C92: 6/29/2023 | E92: CUST031 | F92: PROD001 | G92: Central | H92: 803 | I92: 2 | J92: 1606 | K92: Apple Pay | L92: Delivered | M92: FedEx
A93: ORD0092 | B93: 2/21/2023 | D93: 2/25/2023 | E93: CUST013 | F93: PROD014 | G93: North | H93: 248 | I93: 5 | J93: 1240 | K93: PayPal | L93: Cancelled | M93: UPS
A94: ORD0093 | B94: 2/19/2023 | C94: 2/21/2023 | E94: CUST036 | F94: PROD016 | G94: East | H94: 210 | I94: 3 | J94: 630 | K94: Apple Pay | L94: Delivered | M94: DHL
A95: ORD0094 | B95: 12/5/2023 | D95: 12/12/2023 | E95: CUST013 | F95: PROD004 | G95: North | H95: 62 | I95: 2 | J95: 124 | K95: Credit Card | L95: Cancelled | M95: FedEx
A96: ORD0095 | B96: 6/7/2023 | D96: 6/12/2023 | E96: CUST043 | F96: PROD009 | G96: South | H96: 11 | I96: 5 | J96: 55 | K96: Debit Card | L96: Cancelled | M96: Amazon Logistics
A97: ORD0096 | B97: 7/9/2023 | C97: 7/12/2023 | E97: CUST017 | F97: PROD015 | G97: North | H97: 21 | I97: 2 | J97: 42 | K97: Amazon Pay | L97: Delivered | M97: UPS
A98: ORD0097 | B98: 12/23/2023 | C98: 12/26/2023 | E98: CUST023 | F98: PROD018 | G98: West | H98: 95 | I98: 5 | J98: 475 | K98: Amazon Pay | L98: Delivered | M98: Amazon Logistics
A99: ORD0098 | B99: 9/25/2023 | C99: 9/30/2023 | E99: CUST044 | F99: PROD016 | G99: South | H99: 215 | I99: 2 | J99: 430 | K99: PayPal | L99: Delivered | M99: Amazon Logistics
A100: ORD0099 | B100: 1/18/2023 | D100: 1/24/2023 | E100: CUST034 | F100: PROD019 | G100: West | H100: 43 | I100: 5 | J100: 215 | K100: Credit Card | L100: Cancelled | M100: UPS
...

Sheet ProductMaster
A1: Product ID | B1: Product Name | C1: Category | D1: Cost Price | E1: Description
A2: PROD001 | B2: Smartphone | C2: Electronics | D2: 749 | E2: Latest model with 5G, dual SIM, and OLED display
A3: PROD002 | B3: Action Figure | C3: Toys | D3: 39 | E3: Collectible superhero action figure for ages 8+
A4: PROD003 | B4: Cookware Set | C4: Home | D4: 129 | E4: Non-stick 5-piece cookware set for daily use
A5: PROD004 | B5: Leg Set | C5: Toys | D5: 59 | E5: 300-piece creative building block toy set
A6: PROD005 | B6: T-Shirt | C6: Fashion | D6: 25 | E6: Cotton t-shirt, available in multiple colors
A7: PROD006 | B7: Shoes | C7: Fashion | D7: 89 | E7: Casual wear shoes for men and women
A8: PROD007 | B8: Puzzle | C8: Toys | D8: 29 | E8: 1000-piece jigsaw puzzle
A9: PROD008 | B9: Textbook | C9: Books | D9: 65 | E9: University-level textbook on computer science
A10: PROD009 | B10: Magazine | C10: Books | D10: 10 | E10: Monthly lifestyle magazine
A11: PROD010 | B11: Jeans | C11: Fashion | D11: 55 | E11: Slim fit denim jeans with stretch
A12: PROD011 | B12: Headphones | C12: Electronics | D12: 159 | E12: Wireless noise-cancelling over-ear headphones
A13: PROD012 | B13: Lamp | C13: Home | D13: 42 | E13: LED desk lamp with dimmable light
... A23: PROD022 | B23: Backpack | C23: Fashion | D23: 60 | E23: Waterproof backpack with laptop compartment

Sheet CustomerMaster
A1: Customer ID | B1: Customer Name | C1: Customer Type | D1: City | E1: State
A2: CUST001 | B2: James Miller | C2: Business | D2: New York | E2: New York
A3: CUST002 | B3: Emily Johnson | C3: Prime | D3: Seattle | E3: Washington
A4: CUST003 | B4: Ethan Davis | C4: Prime | D4: Austin | E4: Texas
A5: CUST004 | B5: Noah Wilson | C5: Prime | D5: San Francisco | E5: California
A6: CUST005 | B6: Olivia Martinez | C6: Prime | D6: Seattle | E6: Washington
A7: CUST006 | B7: Ava Robinson | C7: Prime | D7: Chicago | E7: Illinois
A8: CUST007 | B8: Liam Walker | C8: Prime | D8: San Francisco | E8: California
A9: CUST008 | B9: Harper Young | C9: Business | D9: Dallas | E9: Texas
A10: CUST009 | B10: Jackson Allen | C10: Business | D10: Seattle | E10: Washington
A11: CUST010 | B11: Charlotte Harris | C11: Prime | D11: Chicago | E11: Illinois
A12: CUST011 | B12: Mason Hall | C12: Business | D12: Miami | E12: Florida
... A50: CUST049 | B50: Hazel Gray | C50: Business | D50: Chicago | E50: Illinois

Sheet RegionGoals
A1: Region | B1: Sales Target
A2: Central | B2: 97500
A3: East | B3: 50500
A4: North | B4: 105000
A5: South | B5: 91500
A6: West | B6: 90750

Sheet AmazonSales_Clean
A1: Order ID | B1: Order Date | C1: Month | D1: Delivery Date | E1: Cancel Date | F1: Customer ID | G1: Product ID | H1: Region | I1: Sale Price/Unit | J1: Quantity | K1: Sales Amount | L1: Payment Method | M1: Delivery Status | N1: Fulfillment Partner | O1: Product Category | P1: Order Status | Q1: Delivery Days | R1: Delivery Performance | S1: Effective Sales | T1: Customer Name
A2: ORD0001 | B2: 12/31/2023 | C2: =TEXT(B2,"mmm") -> Dec | E2: 1/2/2024 | F2: CUST021 | G2: PROD012 | H2: North | I2: 44 | J2: 1 | K2: 44 | L2: Apple Pay | M2: Cancelled | N2: DHL | O2: =_xlfn.XLOOKUP(G2,ProductMaster!$A$2:$A$23,ProductMaster!$C$2:$C$23,"Not Found") -> Home | P2: =IF(M2="Cancelled","Cancelled",IF(M2="delivered","Delivered","Active")) -> Cancelled | Q2: =IF(M2="delivered",D2-B2,"") | R2: =IF(M2="Delivered",IF(D2-B2<=2,"Fast","Slow"),"Not Delivered") -> Not Delivered | S2: =IF(M2="delivered",K2,0) -> 0 | T2: =_xlfn.XLOOKUP(F2,CustomerMaster!$A$2:$A$50,CustomerMaster!$B$2:$B$50,"Not Found") -> Zoe Mitchell
A3: ORD0002 | B3: 2/22/2023 | C3: =TEXT(B3,"mmm") -> Feb | D3: 2/24/2023 | F3: CUST029 | G3: PROD018 | H3: East | I3: 96 | J3: 4 | K3: 384 | L3: Credit Card | M3: Delivered | N3: DHL | O3: =_xlfn.XLOOKUP(G3,ProductMaster!$A$2:$A$23,ProductMaster!$C$2:$C$23,"Not Found") -> Toys | P3: =IF(M3="Cancelled","Cancelled",IF(M3="delivered","Delivered","Active")) -> Delivered | Q3: =IF(M3="delivered",D3-B3,"") -> 2 | R3: =IF(M3="Delivered",IF(D3-B3<=2,"Fast","Slow"),"Not Delivered") -> Fast | S3: =IF(M3="delivered",K3,0) -> 384 | T3: =_xlfn.XLOOKUP(F3,CustomerMaster!$A$2:$A$50,CustomerMaster!$B$2:$B$50,"Not Found") -> Ava White
A4: ORD0003 | B4: 10/11/2023 | C4: =TEXT(B4,"mmm") -> Oct | F4: CUST021 | G4: PROD013 | H4: South | I4: 194 | J4: 4 | K4: 776 | L4: Credit Card | M4: In Transit | N4: USPS | O4: =_xlfn.XLOOKUP(G4,ProductMaster!$A$2:$A$23,ProductMaster!$C$2:$C$23,"Not Found") -> Home | P4: =IF(M4="Cancelled","Cancelled",IF(M4="delivered","Delivered","Active")) -> Active | Q4: =IF(M4="delivered",D4-B4,"") | R4: =IF(M4="Delivered",IF(D4-B4<=2,"Fast","Slow"),"Not Delivered") -> Not Delivered | S4: =IF(M4="delivered",K4,0) -> 0 | T4: =_xlfn.XLOOKUP(F4,CustomerMaster!$A$2:$A$50,CustomerMaster!$B$2:$B$50,"Not Found") -> Zoe Mitchell
A5: ORD0004 | B5: 5/5/2023 | C5: =TEXT(B5,"mmm") -> May | E5: 5/11/2023 | F5: CUST044 | G5: PROD013 | H5: North | I5: 196 | J5: 3 | K5: 196 | L5: PayPal | M5: Cancelled | N5: UPS | O5: =_xlfn.XLOOKUP(G5,ProductMaster!$A$2:$A$23,ProductMaster!$C$2:$C$23,"Not Found") -> Home | P5: =IF(M5="Cancelled","Cancelled",IF(M5="delivered","Delivered","Active")) -> Cancelled | Q5: =IF(M5="delivered",D5-B5,"") | R5: =IF(M5="Delivered",IF(D5-B5<=2,"Fast","Slow"),"Not Delivered") -> Not Delivered | S5: =IF(M5="delivered",K5,0) -> 0 | T5: =_xlfn.XLOOKUP(F5,CustomerMaster!$A$2:$A$50,CustomerMaster!$B$2:$B$50,"Not Found") -> Grace Ward
A6: ORD0005 | B6: 2/2/2023 | C6: =TEXT(B6,"mmm") -> Feb | D6: 2/5/2023 | F6: CUST027 | G6: PROD010 | H6: North | I6: 59 | J6: 1 | K6: 59 | L6: PayPal | M6: Delivered | N6: Amazon Logistics | O6: =_xlfn.XLOOKUP(G6,ProductMaster!$A$2:$A$23,ProductMaster!$C$2:$C$23,"Not Found") -> Fashion | P6: =IF(M6="Cancelled","Cancelled",IF(M6="delivered","Delivered","Active")) -> Delivered | Q6: =IF(M6="delivered",D6-B6,"") -> 3 | R6: =IF(M6="Delivered",IF(D6-B6<=2,"Fast","Slow"),"Not Delivered") -> Slow | S6: =IF(M6="delivered",K6,0) -> 59 | T6: =_xlfn.XLOOKUP(F6,CustomerMaster!$A$2:$A$50,CustomerMaster!$B$2:$B$50,"Not Found") -> Hazel Brooks
A7: ORD0006 | B7: 11/1/2023 | C7: =TEXT(B7,"mmm") -> Nov | E7: 11/2/2023 | F7: CUST009 | G7: PROD010 | H7: North | I7: 58 | J7: 4 | K7: 58 | L7: Amazon Pay | M7: Cancelled | N7: DHL | O7: =_xlfn.XLOOKUP(G7,ProductMaster!$A$2:$A$23,ProductMaster!$C$2:$C$23,"Not Found") -> Fashion | P7: =IF(M7="Cancelled","Cancelled",IF(M7="delivered","Delivered","Active")) -> Cancelled | Q7: =IF(M7="delivered",D7-B7,"") | R7: =IF(M7="Delivered",IF(D7-B7<=2,"Fast","Slow"),"Not Delivered") -> Not Delivered | S7: =IF(M7="delivered",K7,0) -> 0 | T7: =_xlfn.XLOOKUP(F7,CustomerMaster!$A$2:$A$50,CustomerMaster!$B$2:$B$50,"Not Found") -> Jackson Allen
A8: ORD0007 | B8: 8/14/2023 | C8: =TEXT(B8,"mmm") -> Aug | E8: 8/18/2023 | F8: CUST042 | G8: PROD020 | H8: Central | I8: 105 | J8: 3 | K8: 105 | L8: Debit Card | M8: Cancelled | N8: DHL | O8: =_xlfn.XLOOKUP(G8,ProductMaster!$A$2:$A$23,ProductMaster!$C$2:$C$23,"Not Found") -> Electronics | P8: =IF(M8="Cancelled","Cancelled",IF(M8="delivered","Delivered","Active")) -> Cancelled | Q8: =IF(M8="delivered",D8-B8,"") | R8: =IF(M8="Delivered",IF(D8-B8<=2,"Fast","Slow"),"Not Delivered") -> Not Delivered | S8: =IF(M8="delivered",K8,0) -> 0 | T8: =_xlfn.XLOOKUP(F8,CustomerMaster!$A$2:$A$50,CustomerMaster!$B$2:$B$50,"Not Found") -> Noah Wilson
A9: ORD0008 | B9: 4/1/2023 | C9: =TEXT(B9,"mmm") -> Apr | E9: 4/6/2023 | F9: CUST019 | G9: PROD021 | H9: West | I9: 37 | J9: 5 | K9: 37 | L9: PayPal | M9: Cancelled | N9: DHL | O9: =_xlfn.XLOOKUP(G9,ProductMaster!$A$2:$A$23,ProductMaster!$C$2:$C$23,"Not Found") -> Home | P9: =IF(M9="Cancelled","Cancelled",IF(M9="delivered","Delivered","Active")) -> Cancelled | Q9: =IF(M9="delivered",D9-B9,"") | R9: =IF(M9="Delivered",IF(D9-B9<=2,"Fast","Slow"),"Not Delivered") -> Not Delivered | S9: =IF(M9="delivered",K9,0) -> 0 | T9: =_xlfn.XLOOKUP(F9,CustomerMaster!$A$2:$A$50,CustomerMaster!$B$2:$B$50,"Not Found") -> Ava Robinson
A10: ORD0009 | B10: 7/21/2023 | C10: =TEXT(B10,"mmm") -> Jul | F10: CUST013 | G10: PROD019 | H10: Central | I10: 44 | J10: 2 | K10: 88 | L10: Credit Card | M10: In Transit | N10: Amazon Logistics | O10: =_xlfn.XLOOKUP(G10,ProductMaster!$A$2:$A$23,ProductMaster!$C$2:$C$23,"Not Found") -> Fashion | P10: =IF(M10="Cancelled","Cancelled",IF(M10="delivered","Delivered","Active")) -> Active | Q10: =IF(M10="delivered",D10-B10,"") | R10: =IF(M10="Delivered",IF(D10-B10<=2,"Fast","Slow"),"Not Delivered") -> Not Delivered | S10: =IF(M10="delivered",K10,0) -> 0 | T10: =_xlfn.XLOOKUP(F10,CustomerMaster!$A$2:$A$50,CustomerMaster!$B$2:$B$50,"Not Found") -> Olivia Martinez
A11: ORD0010 | B11: 12/29/2023 | C11: =TEXT(B11,"mmm") -> Dec | F11: CUST019 | G11: PROD003 | H11: South | I11: 141 | J11: 4 | K11: 564 | L11: Debit Card | M11: In Transit | N11: DHL | O11: =_xlfn.XLOOKUP(G11,ProductMaster!$A$2:$A$23,ProductMaster!$C$2:$C$23,"Not Found") -> Home | P11: =IF(M11="Cancelled","Cancelled",IF(M11="delivered","Delivered","Active")) -> Active | Q11: =IF(M11="delivered",D11-B11,"") | R11: =IF(M11="Delivered",IF(D11-B11<=2,"Fast","Slow"),"Not Delivered") -> Not Delivered | S11: =IF(M11="delivered",K11,0) -> 0 | T11: =_xlfn.XLOOKUP(F11,CustomerMaster!$A$2:$A$50,CustomerMaster!$B$2:$B$50,"Not Found") -> Ava Robinson
A12: ORD0011 | B12: 5/4/2023 | C12: =TEXT(B12,"mmm") -> May | E12: 5/8/2023 | F12: CUST046 | G12: PROD014 | H12: South | I12: 249 | J12: 1 | K12: 249 | L12: Amazon Pay | M12: Cancelled | N12: USPS | O12: =_xlfn.XLOOKUP(G12,ProductMaster!$A$2:$A$23,ProductMaster!$C$2:$C$23,"Not Found") -> Electronics | P12: =IF(M12="Cancelled","Cancelled",IF(M12="delivered","Delivered","Active")) -> Cancelled | Q12: =IF(M12="delivered",D12-B12,"") | R12: =IF(M12="Delivered",IF(D12-B12<=2,"Fast","Slow"),"Not Delivered") -> Not Delivered | S12: =IF(M12="delivered",K12,0) -> 0 | T12: =_xlfn.XLOOKUP(F12,CustomerMaster!$A$2:$A$50,CustomerMaster!$B$2:$B$50,"Not Found") -> Emily Johnson
A13: ORD0012 | B13: 7/25/2023 | C13: =TEXT(B13,"mmm") -> Jul | F13: CUST045 | G13: PROD014 | H13: Central | I13: 247 | J13: 3 | K13: 741 | L13: Amazon Pay | M13: In Transit | N13: FedEx | O13: =_xlfn.XLOOKUP(G13,ProductMaster!$A$2:$A$23,ProductMaster!$C$2:$C$23,"Not Found") -> Electronics | P13: =IF(M13="Cancelled","Cancelled",IF(M13="delivered","Delivered","Active")) -> Active | Q13: =IF(M13="delivered",D13-B13,"") | R13: =IF(M13="Delivered",IF(D13-B13<=2,"Fast","Slow"),"Not Delivered") -> Not Delivered | S13: =IF(M13="delivered",K13,0) -> 0 | T13: =_xlfn.XLOOKUP(F13,CustomerMaster!$A$2:$A$50,CustomerMaster!$B$2:$B$50,"Not Found") -> Emily Johnson
A14: ORD0013 | B14: 2/25/2023 | C14: =TEXT(B14,"mmm") -> Feb | E14: 2/28/2023 | F14: CUST023 | G14: PROD006 | H14: Central | I14: 96 | J14: 1 | K14: 96 | L14: Apple Pay | M14: Cancelled | N14: Amazon Logistics | O14: =_xlfn.XLOOKUP(G14,ProductMaster!$A$2:$A$23,ProductMaster!$C$2:$C$23,"Not Found") -> Fashion | P14: =IF(M14="Cancelled","Cancelled",IF(M14="delivered","Delivered","Active")) -> Cancelled | Q14: =IF(M14="delivered",D14-B14,"") | R14: =IF(M14="Delivered",IF(D14-B14<=2,"Fast","Slow"),"Not Delivered") -> Not Delivered | S14: =IF(M14="delivered",K14,0) -> 0 | T14: =_xlfn.XLOOKUP(F14,CustomerMaster!$A$2:$A$50,CustomerMaster!$B$2:$B$50,"Not Found") -> Charlotte Reed
A15: ORD0014 | B15: 2/24/2023 | C15: =TEXT(B15,"mmm") -> Feb | E15: 2/25/2023 | F15: CUST033 | G15: PROD017 | H15: West | I15: 74 | J15: 5 | K15: 74 | L15: Apple Pay | M15: Cancelled | N15: Amazon Logistics | O15: =_xlfn.XLOOKUP(G15,ProductMaster!$A$2:$A$23,ProductMaster!$C$2:$C$23,"Not Found") -> Electronics | P15: =IF(M15="Cancelled","Cancelled",IF(M15="delivered","Delivered","Active")) -> Cancelled | Q15: =IF(M15="delivered",D15-B15,"") | R15: =IF(M15="Delivered",IF(D15-B15<=2,"Fast","Slow"),"Not Delivered") -> Not Delivered | S15: =IF(M15="delivered",K15,0) -> 0 | T15: =_xlfn.XLOOKUP(F15,CustomerMaster!$A$2:$A$50,CustomerMaster!$B$2:$B$50,"Not Found") -> Hazel Rivera
A16: ORD0015 | B16: 8/26/2023 | C16: =TEXT(B16,"mmm") -> Aug | E16: 9/2/2023 | F16: CUST033 | G16: PROD005 | H16: South | I16: 27 | J16: 1 | K16: 27 | L16: Credit Card | M16: Cancelled | N16: Amazon Logistics | O16: =_xlfn.XLOOKUP(G16,ProductMaster!$A$2:$A$23,ProductMaster!$C$2:$C$23,"Not Found") -> Fashion | P16: =IF(M16="Cancelled","Cancelled",IF(M16="delivered","Delivered","Active")) -> Cancelled | Q16: =IF(M16="delivered",D16-B16,"") | R16: =IF(M16="Delivered",IF(D16-B16<=2,"Fast","Slow"),"Not Delivered") -> Not Delivered | S16: =IF(M16="delivered",K16,0) -> 0 | T16: =_xlfn.XLOOKUP(F16,CustomerMaster!$A$2:$A$50,CustomerMaster!$B$2:$B$50,"Not Found") -> Hazel Rivera
A17: ORD0016 | B17: 2/13/2023 | C17: =TEXT(B17,"mmm") -> Feb | F17: CUST047 | G17: PROD005 | H17: South | I17: 27 | J17: 3 | K17: 81 | L17: Debit Card | M17: In Transit | N17: Amazon Logistics | O17: =_xlfn.XLOOKUP(G17,ProductMaster!$A$2:$A$23,ProductMaster!$C$2:$C$23,"Not Found") -> Fashion | P17: =IF(M17="Cancelled","Cancelled",IF(M17="delivered","Delivered","Active")) -> Active | Q17: =IF(M17="delivered",D17-B17,"") | R17: =IF(M17="Delivered",IF(D17-B17<=2,"Fast","Slow"),"Not Delivered") -> Not Delivered | S17: =IF(M17="delivered",K17,0) -> 0 | T17: =_xlfn.XLOOKUP(F17,CustomerMaster!$A$2:$A$50,CustomerMaster!$B$2:$B$50,"Not Found") -> Scarlett Murphy
A18: ORD0017 | B18: 6/28/2023 | C18: =TEXT(B18,"mmm") -> Jun | D18: 7/1/2023 | F18: CUST045 | G18: PROD015 | H18: East | I18: 21 | J18: 3 | K18: 63 | L18: Credit Card | M18: Delivered | N18: DHL | O18: =_xlfn.XLOOKUP(G18,ProductMaster!$A$2:$A$23,ProductMaster!$C$2:$C$23,"Not Found") -> Books | P18: =IF(M18="Cancelled","Cancelled",IF(M18="delivered","Delivered","Active")) -> Delivered | Q18: =IF(M18="delivered",D18-B18,"") -> 3 | R18: =IF(M18="Delivered",IF(D18-B18<=2,"Fast","Slow"),"Not Delivered") -> Slow | S18: =IF(M18="delivered",K18,0) -> 63 | T18: =_xlfn.XLOOKUP(F18,CustomerMaster!$A$2:$A$50,CustomerMaster!$B$2:$B$50,"Not Found") -> Emily Johnson
A19: ORD0018 | B19: 11/28/2023 | C19: =TEXT(B19,"mmm") -> Nov | F19: CUST011 | G19: PROD008 | H19: West | I19: 70 | J19: 5 | K19: 350 | L19: PayPal | M19: In Transit | N19: Amazon Logistics | O19: =_xlfn.XLOOKUP(G19,ProductMaster!$A$2:$A$23,ProductMaster!$C$2:$C$23,"Not Found") -> Books | P19: =IF(M19="Cancelled","Cancelled",IF(M19="delivered","Delivered","Active")) -> Active | Q19: =IF(M19="delivered",D19-B19,"") | R19: =IF(M19="Delivered",IF(D19-B19<=2,"Fast","Slow"),"Not Delivered") -> Not Delivered | S19: =IF(M19="delivered",K19,0) -> 0 | T19: =_xlfn.XLOOKUP(F19,CustomerMaster!$A$2:$A$50,CustomerMaster!$B$2:$B$50,"Not Found") -> Mason Hall
A20: ORD0019 | B20: 8/25/2023 | C20: =TEXT(B20,"mmm") -> Aug | F20: CUST041 | G20: PROD006 | H20: South | I20: 94 | J20: 4 | K20: 376 | L20: Credit Card | M20: In Transit | N20: USPS | O20: =_xlfn.XLOOKUP(G20,ProductMaster!$A$2:$A$23,ProductMaster!$C$2:$C$23,"Not Found") -> Fashion | P20: =IF(M20="Cancelled","Cancelled",IF(M20="delivered","Delivered","Active")) -> Active | Q20: =IF(M20="delivered",D20-B20,"") | R20: =IF(M20="Delivered",IF(D20-B20<=2,"Fast","Slow"),"Not Delivered") -> Not Delivered | S20: =IF(M20="delivered",K20,0) -> 0 | T20: =_xlfn.XLOOKUP(F20,CustomerMaster!$A$2:$A$50,CustomerMaster!$B$2:$B$50,"Not Found") -> Jacob Price
A21: ORD0020 | B21: 4/12/2023 | C21: =TEXT(B21,"mmm") -> Apr | F21: CUST025 | G21: PROD001 | H21: North | I21: 813 | J21: 2 | K21: 1626 | L21: Credit Card | M21: In Transit | N21: FedEx | O21: =_xlfn.XLOOKUP(G21,ProductMaster!$A$2:$A$23,ProductMaster!$C$2:$C$23,"Not Found") -> Electronics | P21: =IF(M21="Cancelled","Cancelled",IF(M21="delivered","Delivered","Active")) -> Active | Q21: =IF(M21="delivered",D21-B21,"") | R21: =IF(M21="Delivered",IF(D21-B21<=2,"Fast","Slow"),"Not Delivered") -> Not Delivered | S21: =IF(M21="delivered",K21,0) -> 0 | T21: =_xlfn.XLOOKUP(F21,CustomerMaster!$A$2:$A$50,CustomerMaster!$B$2:$B$50,"Not Found") -> Emma King
A22: ORD0021 | B22: 10/2/2023 | C22: =TEXT(B22,"mmm") -> Oct | F22: CUST013 | G22: PROD015 | H22: Central | I22: 21 | J22: 4 | K22: 84 | L22: PayPal | M22: In Transit | N22: Amazon Logistics | O22: =_xlfn.XLOOKUP(G22,ProductMaster!$A$2:$A$23,ProductMaster!$C$2:$C$23,"Not Found") -> Books | P22: =IF(M22="Cancelled","Cancelled",IF(M22="delivered","Delivered","Active")) -> Active | Q22: =IF(M22="delivered",D22-B22,"") | R22: =IF(M22="Delivered",IF(D22-B22<=2,"Fast","Slow"),"Not Delivered") -> Not Delivered | S22: =IF(M22="delivered",K22,0) -> 0 | T22: =_xlfn.XLOOKUP(F22,CustomerMaster!$A$2:$A$50,CustomerMaster!$B$2:$B$50,"Not Found") -> Olivia Martinez
A23: ORD0022 | B23: 11/9/2023 | C23: =TEXT(B23,"mmm") -> Nov | F23: CUST023 | G23: PROD012 | H23: West | I23: 46 | J23: 5 | K23: 230 | L23: PayPal | M23: In Transit | N23: USPS | O23: =_xlfn.XLOOKUP(G23,ProductMaster!$A$2:$A$23,ProductMaster!$C$2:$C$23,"Not Found") -> Home | P23: =IF(M23="Cancelled","Cancelled",IF(M23="delivered","Delivered","Active")) -> Active | Q23: =IF(M23="delivered",D23-B23,"") | R23: =IF(M23="Delivered",IF(D23-B23<=2,"Fast","Slow"),"Not Delivered") -> Not Delivered | S23: =IF(M23="delivered",K23,0) -> 0 | T23: =_xlfn.XLOOKUP(F23,CustomerMaster!$A$2:$A$50,CustomerMaster!$B$2:$B$50,"Not Found") -> Charlotte Reed
A24: ORD0023 | B24: 2/13/2023 | C24: =TEXT(B24,"mmm") -> Feb | E24: 2/14/2023 | F24: CUST016 | G24: PROD010 | H24: West | I24: 58 | J24: 3 | K24: 58 | L24: Amazon Pay | M24: Cancelled | N24: Amazon Logistics | O24: =_xlfn.XLOOKUP(G24,ProductMaster!$A$2:$A$23,ProductMaster!$C$2:$C$23,"Not Found") -> Fashion | P24: =IF(M24="Cancelled","Cancelled",IF(M24="delivered","Delivered","Active")) -> Cancelled | Q24: =IF(M24="delivered",D24-B24,"") | R24: =IF(M24="Delivered",IF(D24-B24<=2,"Fast","Slow"),"Not Delivered") -> Not Delivered | S24: =IF(M24="delivered",K24,0) -> 0 | T24: =_xlfn.XLOOKUP(F24,CustomerMaster!$A$2:$A$50,CustomerMaster!$B$2:$B$50,"Not Found") -> Elijah Lewis
A25: ORD0024 | B25: 11/2/2023 | C25: =TEXT(B25,"mmm") -> Nov | D25: 11/5/2023 | F25: CUST028 | G25: PROD006 | H25: West | I25: 96 | J25: 5 | K25: 480 | L25: Amazon Pay | M25: Delivered | N25: Amazon Logistics | O25: =_xlfn.XLOOKUP(G25,ProductMaster!$A$2:$A$23,ProductMaster!$C$2:$C$23,"Not Found") -> Fashion | P25: =IF(M25="Cancelled","Cancelled",IF(M25="delivered","Delivered","Active")) -> Delivered | Q25: =IF(M25="delivered",D25-B25,"") -> 3 | R25: =IF(M25="Delivered",IF(D25-B25<=2,"Fast","Slow"),"Not Delivered") -> Slow | S25: =IF(M25="delivered",K25,0) -> 480 | T25: =_xlfn.XLOOKUP(F25,CustomerMaster!$A$2:$A$50,CustomerMaster!$B$2:$B$50,"Not Found") -> Lily Bennett
A26: ORD0025 | B26: 5/28/2023 | C26: =TEXT(B26,"mmm") -> May | D26: 5/30/2023 | F26: CUST040 | G26: PROD002 | H26: South | I26: 43 | J26: 1 | K26: 43 | L26: Debit Card | M26: Delivered | N26: Amazon Logistics | O26: =_xlfn.XLOOKUP(G26,ProductMaster!$A$2:$A$23,ProductMaster!$C$2:$C$23,"Not Found") -> Toys | P26: =IF(M26="Cancelled","Cancelled",IF(M26="delivered","Delivered","Active")) -> Delivered | Q26: =IF(M26="delivered",D26-B26,"") -> 2 | R26: =IF(M26="Delivered",IF(D26-B26<=2,"Fast","Slow"),"Not Delivered") -> Fast | S26: =IF(M26="delivered",K26,0) -> 43 | T26: =_xlfn.XLOOKUP(F26,CustomerMaster!$A$2:$A$50,CustomerMaster!$B$2:$B$50,"Not Found") -> Benjamin Clark
A27: ORD0026 | B27: 10/15/2023 | C27: =TEXT(B27,"mmm") -> Oct | D27: 10/21/2023 | F27: CUST027 | G27: PROD022 | H27: South | I27: 64 | J27: 4 | K27: 256 | L27: Debit Card | M27: Delivered | N27: USPS | O27: =_xlfn.XLOOKUP(G27,ProductMaster!$A$2:$A$23,ProductMaster!$C$2:$C$23,"Not Found") -> Fashion | P27: =IF(M27="Cancelled","Cancelled",IF(M27="delivered","Delivered","Active")) -> Delivered | Q27: =IF(M27="delivered",D27-B27,"") -> 6 | R27: =IF(M27="Delivered",IF(D27-B27<=2,"Fast","Slow"),"Not Delivered") -> Slow | S27: =IF(M27="delivered",K27,0) -> 256 | T27: =_xlfn.XLOOKUP(F27,CustomerMaster!$A$2:$A$50,CustomerMaster!$B$2:$B$50,"Not Found") -> Hazel Brooks
A28: ORD0027 | B28: 1/16/2023 | C28: =TEXT(B28,"mmm") -> Jan | F28: CUST018 | G28: PROD008 | H28: South | I28: 70 | J28: 2 | K28: 140 | L28: Amazon Pay | M28: In Transit | N28: Amazon Logistics | O28: =_xlfn.XLOOKUP(G28,ProductMaster!$A$2:$A$23,ProductMaster!$C$2:$C$23,"Not Found") -> Books | P28: =IF(M28="Cancelled","Cancelled",IF(M28="delivered","Delivered","Active")) -> Active | Q28: =IF(M28="delivered",D28-B28,"") | R28: =IF(M28="Delivered",IF(D28-B28<=2,"Fast","Slow"),"Not Delivered") -> Not Delivered | S28: =IF(M28="delivered",K28,0) -> 0 | T28: =_xlfn.XLOOKUP(F28,CustomerMaster!$A$2:$A$50,CustomerMaster!$B$2:$B$50,"Not Found") -> Grace Scott
A29: ORD0028 | B29: 10/9/2023 | C29: =TEXT(B29,"mmm") -> Oct | F29: CUST018 | G29: PROD018 | H29: Central | I29: 97 | J29: 3 | K29: 291 | L29: Credit Card | M29: In Transit | N29: Amazon Logistics | O29: =_xlfn.XLOOKUP(G29,ProductMaster!$A$2:$A$23,ProductMaster!$C$2:$C$23,"Not Found") -> Toys | P29: =IF(M29="Cancelled","Cancelled",IF(M29="delivered","Delivered","Active")) -> Active | Q29: =IF(M29="delivered",D29-B29,"") | R29: =IF(M29="Delivered",IF(D29-B29<=2,"Fast","Slow"),"Not Delivered") -> Not Delivered | S29: =IF(M29="delivered",K29,0) -> 0 | T29: =_xlfn.XLOOKUP(F29,CustomerMaster!$A$2:$A$50,CustomerMaster!$B$2:$B$50,"Not Found") -> Grace Scott
A30: ORD0029 | B30: 10/7/2023 | C30: =TEXT(B30,"mmm") -> Oct | E30: 10/10/2023 | F30: CUST007 | G30: PROD021 | H30: East | I30: 37 | J30: 3 | K30: 37 | L30: Apple Pay | M30: Cancelled | N30: DHL | O30: =_xlfn.XLOOKUP(G30,ProductMaster!$A$2:$A$23,ProductMaster!$C$2:$C$23,"Not Found") -> Home | P30: =IF(M30="Cancelled","Cancelled",IF(M30="delivered","Delivered","Active")) -> Cancelled | Q30: =IF(M30="delivered",D30-B30,"") | R30: =IF(M30="Delivered",IF(D30-B30<=2,"Fast","Slow"),"Not Delivered") -> Not Delivered | S30: =IF(M30="delivered",K30,0) -> 0 | T30: =_xlfn.XLOOKUP(F30,CustomerMaster!$A$2:$A$50,CustomerMaster!$B$2:$B$50,"Not Found") -> Liam Walker
A31: ORD0030 | B31: 2/14/2023 | C31: =TEXT(B31,"mmm") -> Feb | F31: CUST008 | G31: PROD008 | H31: North | I31: 69 | J31: 5 | K31: 345 | L31: Amazon Pay | M31: In Transit | N31: Amazon Logistics | O31: =_xlfn.XLOOKUP(G31,ProductMaster!$A$2:$A$23,ProductMaster!$C$2:$C$23,"Not Found") -> Books | P31: =IF(M31="Cancelled","Cancelled",IF(M31="delivered","Delivered","Active")) -> Active | Q31: =IF(M31="delivered",D31-B31,"") | R31: =IF(M31="Delivered",IF(D31-B31<=2,"Fast","Slow"),"Not Delivered") -> Not Delivered | S31: =IF(M31="delivered",K31,0) -> 0 | T31: =_xlfn.XLOOKUP(F31,CustomerMaster!$A$2:$A$50,CustomerMaster!$B$2:$B$50,"Not Found") -> Harper Young
A32: ORD0031 | B32: 3/26/2023 | C32: =TEXT(B32,"mmm") -> Mar | F32: CUST014 | G32: PROD002 | H32: North | I32: 42 | J32: 5 | K32: 210 | L32: Amazon Pay | M32: In Transit | N32: UPS | O32: =_xlfn.XLOOKUP(G32,ProductMaster!$A$2:$A$23,ProductMaster!$C$2:$C$23,"Not Found") -> Toys | P32: =IF(M32="Cancelled","Cancelled",IF(M32="delivered","Delivered","Active")) -> Active | Q32: =IF(M32="delivered",D32-B32,"") | R32: =IF(M32="Delivered",IF(D32-B32<=2,"Fast","Slow"),"Not Delivered") -> Not Delivered | S32: =IF(M32="delivered",K32,0) -> 0 | T32: =_xlfn.XLOOKUP(F32,CustomerMaster!$A$2:$A$50,CustomerMaster!$B$2:$B$50,"Not Found") -> Harper Young
A33: ORD0032 | B33: 6/15/2023 | C33: =TEXT(B33,"mmm") -> Jun | E33: 6/22/2023 | F33: CUST037 | G33: PROD009 | H33: East | I33: 11 | J33: 5 | K33: 11 | L33: Debit Card | M33: Cancelled | N33: FedEx | O33: =_xlfn.XLOOKUP(G33,ProductMaster!$A$2:$A$23,ProductMaster!$C$2:$C$23,"Not Found") -> Books | P33: =IF(M33="Cancelled","Cancelled",IF(M33="delivered","Delivered","Active")) -> Cancelled | Q33: =IF(M33="delivered",D33-B33,"") | R33: =IF(M33="Delivered",IF(D33-B33<=2,"Fast","Slow"),"Not Delivered") -> Not Delivered | S33: =IF(M33="delivered",K33,0) -> 0 | T33: =_xlfn.XLOOKUP(F33,CustomerMaster!$A$2:$A$50,CustomerMaster!$B$2:$B$50,"Not Found") -> Emily Johnson
A34: ORD0033 | B34: 5/22/2023 | C34: =TEXT(B34,"mmm") -> May | D34: 5/23/2023 | F34: CUST016 | G34: PROD005 | H34: South | I34: 27 | J34: 2 | K34: 54 | L34: Apple Pay | M34: Delivered | N34: USPS | O34: =_xlfn.XLOOKUP(G34,ProductMaster!$A$2:$A$23,ProductMaster!$C$2:$C$23,"Not Found") -> Fashion | P34: =IF(M34="Cancelled","Cancelled",IF(M34="delivered","Delivered","Active")) -> Delivered | Q34: =IF(M34="delivered",D34-B34,"") -> 1 | R34: =IF(M34="Delivered",IF(D34-B34<=2,"Fast","Slow"),"Not Delivered") -> Fast | S34: =IF(M34="delivered",K34,0) -> 54 | T34: =_xlfn.XLOOKUP(F34,CustomerMaster!$A$2:$A$50,CustomerMaster!$B$2:$B$50,"Not Found") -> Elijah Lewis
A35: ORD0034 | B35: 11/20/2023 | C35: =TEXT(B35,"mmm") -> Nov | F35: CUST025 | G35: PROD015 | H35: South | I35: 21 | J35: 1 | K35: 21 | L35: Amazon Pay | M35: In Transit | N35: DHL | O35: =_xlfn.XLOOKUP(G35,ProductMaster!$A$2:$A$23,ProductMaster!$C$2:$C$23,"Not Found") -> Books | P35: =IF(M35="Cancelled","Cancelled",IF(M35="delivered","Delivered","Active")) -> Active | Q35: =IF(M35="delivered",D35-B35,"") | R35: =IF(M35="Delivered",IF(D35-B35<=2,"Fast","Slow"),"Not Delivered") -> Not Delivered | S35: =IF(M35="delivered",K35,0) -> 0 | T35: =_xlfn.XLOOKUP(F35,CustomerMaster!$A$2:$A$50,CustomerMaster!$B$2:$B$50,"Not Found") -> Emma King
A36: ORD0035 | B36: 12/22/2023 | C36: =TEXT(B36,"mmm") -> Dec | D36: 12/26/2023 | F36: CUST032 | G36: PROD011 | H36: South | I36: 172 | J36: 1 | K36: 172 | L36: PayPal | M36: Delivered | N36: USPS | O36: =_xlfn.XLOOKUP(G36,ProductMaster!$A$2:$A$23,ProductMaster!$C$2:$C$23,"Not Found") -> Electronics | P36: =IF(M36="Cancelled","Cancelled",IF(M36="delivered","Delivered","Active")) -> Delivered | Q36: =IF(M36="delivered",D36-B36,"") -> 4 | R36: =IF(M36="Delivered",IF(D36-B36<=2,"Fast","Slow"),"Not Delivered") -> Slow | S36: =IF(M36="delivered",K36,0) -> 172 | T36: =_xlfn.XLOOKUP(F36,CustomerMaster!$A$2:$A$50,CustomerMaster!$B$2:$B$50,"Not Found") -> Luke Gray
A37: ORD0036 | B37: 7/23/2023 | C37: =TEXT(B37,"mmm") -> Jul | F37: CUST014 | G37: PROD016 | H37: North | I37: 212 | J37: 3 | K37: 636 | L37: Amazon Pay | M37: In Transit | N37: UPS | O37: =_xlfn.XLOOKUP(G37,ProductMaster!$A$2:$A$23,ProductMaster!$C$2:$C$23,"Not Found") -> Home | P37: =IF(M37="Cancelled","Cancelled",IF(M37="delivered","Delivered","Active")) -> Active | Q37: =IF(M37="delivered",D37-B37,"") | R37: =IF(M37="Delivered",IF(D37-B37<=2,"Fast","Slow"),"Not Delivered") -> Not Delivered | S37: =IF(M37="delivered",K37,0) -> 0 | T37: =_xlfn.XLOOKUP(F37,CustomerMaster!$A$2:$A$50,CustomerMaster!$B$2:$B$50,"Not Found") -> Harper Young
A38: ORD0037 | B38: 10/17/2023 | C38: =TEXT(B38,"mmm") -> Oct | D38: 10/22/2023 | F38: CUST044 | G38: PROD002 | H38: East | I38: 41 | J38: 4 | K38: 164 | L38: Credit Card | M38: Delivered | N38: Amazon Logistics | O38: =_xlfn.XLOOKUP(G38,ProductMaster!$A$2:$A$23,ProductMaster!$C$2:$C$23,"Not Found") -> Toys | P38: =IF(M38="Cancelled","Cancelled",IF(M38="delivered","Delivered","Active")) -> Delivered | Q38: =IF(M38="delivered",D38-B38,"") -> 5 | R38: =IF(M38="Delivered",IF(D38-B38<=2,"Fast","Slow"),"Not Delivered") -> Slow | S38: =IF(M38="delivered",K38,0) -> 164 | T38: =_xlfn.XLOOKUP(F38,CustomerMaster!$A$2:$A$50,CustomerMaster!$B$2:$B$50,"Not Found") -> Grace Ward
A39: ORD0038 | B39: 8/22/2023 | C39: =TEXT(B39,"mmm") -> Aug | E39: 8/24/2023 | F39: CUST028 | G39: PROD007 | H39: North | I39: 32 | J39: 2 | K39: 32 | L39: Debit Card | M39: Cancelled | N39: FedEx | O39: =_xlfn.XLOOKUP(G39,ProductMaster!$A$2:$A$23,ProductMaster!$C$2:$C$23,"Not Found") -> Toys | P39: =IF(M39="Cancelled","Cancelled",IF(M39="delivered","Delivered","Active")) -> Cancelled | Q39: =IF(M39="delivered",D39-B39,"") | R39: =IF(M39="Delivered",IF(D39-B39<=2,"Fast","Slow"),"Not Delivered") -> Not Delivered | S39: =IF(M39="delivered",K39,0) -> 0 | T39: =_xlfn.XLOOKUP(F39,CustomerMaster!$A$2:$A$50,CustomerMaster!$B$2:$B$50,"Not Found") -> Lily Bennett
A40: ORD0039 | B40: 12/2/2023 | C40: =TEXT(B40,"mmm") -> Dec | F40: CUST024 | G40: PROD022 | H40: East | I40: 66 | J40: 2 | K40: 132 | L40: Apple Pay | M40: In Transit | N40: DHL | O40: =_xlfn.XLOOKUP(G40,ProductMaster!$A$2:$A$23,ProductMaster!$C$2:$C$23,"Not Found") -> Fashion | P40: =IF(M40="Cancelled","Cancelled",IF(M40="delivered","Delivered","Active")) -> Active | Q40: =IF(M40="delivered",D40-B40,"") | R40: =IF(M40="Delivered",IF(D40-B40<=2,"Fast","Slow"),"Not Delivered") -> Not Delivered | S40: =IF(M40="delivered",K40,0) -> 0 | T40: =_xlfn.XLOOKUP(F40,CustomerMaster!$A$2:$A$50,CustomerMaster!$B$2:$B$50,"Not Found") -> Scarlett Murphy
A41: ORD0040 | B41: 12/25/2023 | C41: =TEXT(B41,"mmm") -> Dec | F41: CUST006 | G41: PROD004 | H41: East | I41: 62 | J41: 4 | K41: 248 | L41: Debit Card | M41: In Transit | N41: UPS | O41: =_xlfn.XLOOKUP(G41,ProductMaster!$A$2:$A$23,ProductMaster!$C$2:$C$23,"Not Found") -> Toys | P41: =IF(M41="Cancelled","Cancelled",IF(M41="delivered","Delivered","Active")) -> Active | Q41: =IF(M41="delivered",D41-B41,"") | R41: =IF(M41="Delivered",IF(D41-B41<=2,"Fast","Slow"),"Not Delivered") -> Not Delivered | S41: =IF(M41="delivered",K41,0) -> 0 | T41: =_xlfn.XLOOKUP(F41,CustomerMaster!$A$2:$A$50,CustomerMaster!$B$2:$B$50,"Not Found") -> Ava Robinson
A42: ORD0041 | B42: 9/23/2023 | C42: =TEXT(B42,"mmm") -> Sep | D42: 9/30/2023 | F42: CUST001 | G42: PROD011 | H42: West | I42: 173 | J42: 4 | K42: 692 | L42: Apple Pay | M42: Delivered | N42: UPS | O42: =_xlfn.XLOOKUP(G42,ProductMaster!$A$2:$A$23,ProductMaster!$C$2:$C$23,"Not Found") -> Electronics | P42: =IF(M42="Cancelled","Cancelled",IF(M42="delivered","Delivered","Active")) -> Delivered | Q42: =IF(M42="delivered",D42-B42,"") -> 7 | R42: =IF(M42="Delivered",IF(D42-B42<=2,"Fast","Slow"),"Not Delivered") -> Slow | S42: =IF(M42="delivered",K42,0) -> 692 | T42: =_xlfn.XLOOKUP(F42,CustomerMaster!$A$2:$A$50,CustomerMaster!$B$2:$B$50,"Not Found") -> James Miller
A43: ORD0042 | B43: 7/16/2023 | C43: =TEXT(B43,"mmm") -> Jul | D43: 7/18/2023 | F43: CUST007 | G43: PROD004 | H43: West | I43: 63 | J43: 3 | K43: 189 | L43: Apple Pay | M43: Delivered | N43: UPS | O43: =_xlfn.XLOOKUP(G43,ProductMaster!$A$2:$A$23,ProductMaster!$C$2:$C$23,"Not Found") -> Toys | P43: =IF(M43="Cancelled","Cancelled",IF(M43="delivered","Delivered","Active")) -> Delivered | Q43: =IF(M43="delivered",D43-B43,"") -> 2 | R43: =IF(M43="Delivered",IF(D43-B43<=2,"Fast","Slow"),"Not Delivered") -> Fast | S43: =IF(M43="delivered",K43,0) -> 189 | T43: =_xlfn.XLOOKUP(F43,CustomerMaster!$A$2:$A$50,CustomerMaster!$B$2:$B$50,"Not Found") -> Liam Walker
A44: ORD0043 | B44: 2/5/2023 | C44: =TEXT(B44,"mmm") -> Feb | E44: 2/11/2023 | F44: CUST040 | G44: PROD021 | H44: West | I44: 36 | J44: 3 | K44: 36 | L44: Debit Card | M44: Cancelled | N44: USPS | O44: =_xlfn.XLOOKUP(G44,ProductMaster!$A$2:$A$23,ProductMaster!$C$2:$C$23,"Not Found") -> Home | P44: =IF(M44="Cancelled","Cancelled",IF(M44="delivered","Delivered","Active")) -> Cancelled | Q44: =IF(M44="delivered",D44-B44,"") | R44: =IF(M44="Delivered",IF(D44-B44<=2,"Fast","Slow"),"Not Delivered") -> Not Delivered | S44: =IF(M44="delivered",K44,0) -> 0 | T44: =_xlfn.XLOOKUP(F44,CustomerMaster!$A$2:$A$50,CustomerMaster!$B$2:$B$50,"Not Found") -> Benjamin Clark
A45: ORD0044 | B45: 12/18/2023 | C45: =TEXT(B45,"mmm") -> Dec | E45: 12/23/2023 | F45: CUST006 | G45: PROD004 | H45: Central | I45: 62 | J45: 1 | K45: 62 | L45: Apple Pay | M45: Cancelled | N45: Amazon Logistics | O45: =_xlfn.XLOOKUP(G45,ProductMaster!$A$2:$A$23,ProductMaster!$C$2:$C$23,"Not Found") -> Toys | P45: =IF(M45="Cancelled","Cancelled",IF(M45="delivered","Delivered","Active")) -> Cancelled | Q45: =IF(M45="delivered",D45-B45,"") | R45: =IF(M45="Delivered",IF(D45-B45<=2,"Fast","Slow"),"Not Delivered") -> Not Delivered | S45: =IF(M45="delivered",K45,0) -> 0 | T45: =_xlfn.XLOOKUP(F45,CustomerMaster!$A$2:$A$50,CustomerMaster!$B$2:$B$50,"Not Found") -> Ava Robinson
A46: ORD0045 | B46: 6/11/2023 | C46: =TEXT(B46,"mmm") -> Jun | E46: 6/14/2023 | F46: CUST042 | G46: PROD003 | H46: Central | I46: 137 | J46: 5 | K46: 137 | L46: Amazon Pay | M46: Cancelled | N46: FedEx | O46: =_xlfn.XLOOKUP(G46,ProductMaster!$A$2:$A$23,ProductMaster!$C$2:$C$23,"Not Found") -> Home | P46: =IF(M46="Cancelled","Cancelled",IF(M46="delivered","Delivered","Active")) -> Cancelled | Q46: =IF(M46="delivered",D46-B46,"") | R46: =IF(M46="Delivered",IF(D46-B46<=2,"Fast","Slow"),"Not Delivered") -> Not Delivered | S46: =IF(M46="delivered",K46,0) -> 0 | T46: =_xlfn.XLOOKUP(F46,CustomerMaster!$A$2:$A$50,CustomerMaster!$B$2:$B$50,"Not Found") -> Noah Wilson
A47: ORD0046 | B47: 12/4/2023 | C47: =TEXT(B47,"mmm") -> Dec | D47: 12/8/2023 | F47: CUST039 | G47: PROD017 | H47: North | I47: 73 | J47: 4 | K47: 292 | L47: Credit Card | M47: Delivered | N47: Amazon Logistics | O47: =_xlfn.XLOOKUP(G47,ProductMaster!$A$2:$A$23,ProductMaster!$C$2:$C$23,"Not Found") -> Electronics | P47: =IF(M47="Cancelled","Cancelled",IF(M47="delivered","Delivered","Active")) -> Delivered | Q47: =IF(M47="delivered",D47-B47,"") -> 4 | R47: =IF(M47="Delivered",IF(D47-B47<=2,"Fast","Slow"),"Not Delivered") -> Slow | S47: =IF(M47="delivered",K47,0) -> 292 | T47: =_xlfn.XLOOKUP(F47,CustomerMaster!$A$2:$A$50,CustomerMaster!$B$2:$B$50,"Not Found") -> Logan Ramirez
A48: ORD0047 | B48: 7/17/2023 | C48: =TEXT(B48,"mmm") -> Jul | D48: 7/19/2023 | F48: CUST041 | G48: PROD020 | H48: North | I48: 104 | J48: 1 | K48: 104 | L48: PayPal | M48: Delivered | N48: Amazon Logistics | O48: =_xlfn.XLOOKUP(G48,ProductMaster!$A$2:$A$23,ProductMaster!$C$2:$C$23,"Not Found") -> Electronics | P48: =IF(M48="Cancelled","Cancelled",IF(M48="delivered","Delivered","Active")) -> Delivered | Q48: =IF(M48="delivered",D48-B48,"") -> 2 | R48: =IF(M48="Delivered",IF(D48-B48<=2,"Fast","Slow"),"Not Delivered") -> Fast | S48: =IF(M48="delivered",K48,0) -> 104 | T48: =_xlfn.XLOOKUP(F48,CustomerMaster!$A$2:$A$50,CustomerMaster!$B$2:$B$50,"Not Found") -> Jacob Price
A49: ORD0048 | B49: 10/19/2023 | C49: =TEXT(B49,"mmm") -> Oct | D49: 10/24/2023 | F49: CUST044 | G49: PROD006 | H49: East | I49: 97 | J49: 1 | K49: 97 | L49: Amazon Pay | M49: Delivered | N49: FedEx | O49: =_xlfn.XLOOKUP(G49,ProductMaster!$A$2:$A$23,ProductMaster!$C$2:$C$23,"Not Found") -> Fashion | P49: =IF(M49="Cancelled","Cancelled",IF(M49="delivered","Delivered","Active")) -> Delivered | Q49: =IF(M49="delivered",D49-B49,"") -> 5 | R49: =IF(M49="Delivered",IF(D49-B49<=2,"Fast","Slow"),"Not Delivered") -> Slow | S49: =IF(M49="delivered",K49,0) -> 97 | T49: =_xlfn.XLOOKUP(F49,CustomerMaster!$A$2:$A$50,CustomerMaster!$B$2:$B$50,"Not Found") -> Grace Ward
A50: ORD0049 | B50: 5/15/2023 | C50: =TEXT(B50,"mmm") -> May | F50: CUST026 | G50: PROD017 | H50: South | I50: 73 | J50: 5 | K50: 365 | L50: Apple Pay | M50: In Transit | N50: Amazon Logistics | O50: =_xlfn.XLOOKUP(G50,ProductMaster!$A$2:$A$23,ProductMaster!$C$2:$C$23,"Not Found") -> Electronics | P50: =IF(M50="Cancelled","Cancelled",IF(M50="delivered","Delivered","Active")) -> Active | Q50: =IF(M50="delivered",D50-B50,"") | R50: =IF(M50="Delivered",IF(D50-B50<=2,"Fast","Slow"),"Not Delivered") -> Not Delivered | S50: =IF(M50="delivered",K50,0) -> 0 | T50: =_xlfn.XLOOKUP(F50,CustomerMaster!$A$2:$A$50,CustomerMaster!$B$2:$B$50,"Not Found") -> Zoe Mitchell
A51: ORD0050 | B51: 2/12/2023 | C51: =TEXT(B51,"mmm") -> Feb | D51: 2/19/2023 | F51: CUST040 | G51: PROD005 | H51: East | I51: 27 | J51: 3 | K51: 81 | L51: Amazon Pay | M51: Delivered | N51: UPS | O51: =_xlfn.XLOOKUP(G51,ProductMaster!$A$2:$A$23,ProductMaster!$C$2:$C$23,"Not Found") -> Fashion | P51: =IF(M51="Cancelled","Cancelled",IF(M51="delivered","Delivered","Active")) -> Delivered | Q51: =IF(M51="delivered",D51-B51,"") -> 7 | R51: =IF(M51="Delivered",IF(D51-B51<=2,"Fast","Slow"),"Not Delivered") -> Slow | S51: =IF(M51="delivered",K51,0) -> 81 | T51: =_xlfn.XLOOKUP(F51,CustomerMaster!$A$2:$A$50,CustomerMaster!$B$2:$B$50,"Not Found") -> Benjamin Clark
A52: ORD0051 | B52: 10/2/2023 | C52: =TEXT(B52,"mmm") -> Oct | F52: CUST041 | G52: PROD021 | H52: North | I52: 37 | J52: 1 | K52: 37 | L52: Apple Pay | M52: In Transit | N52: UPS | O52: =_xlfn.XLOOKUP(G52,ProductMaster!$A$2:$A$23,ProductMaster!$C$2:$C$23,"Not Found") -> Home | P52: =IF(M52="Cancelled","Cancelled",IF(M52="delivered","Delivered","Active")) -> Active | Q52: =IF(M52="delivered",D52-B52,"") | R52: =IF(M52="Delivered",IF(D52-B52<=2,"Fast","Slow"),"Not Delivered") -> Not Delivered | S52: =IF(M52="delivered",K52,0) -> 0 | T52: =_xlfn.XLOOKUP(F52,CustomerMaster!$A$2:$A$50,CustomerMaster!$B$2:$B$50,"Not Found") -> Jacob Price
A53: ORD0052 | B53: 1/30/2023 | C53: =TEXT(B53,"mmm") -> Jan | D53: 2/1/2023 | F53: CUST008 | G53: PROD015 | H53: North | I53: 22 | J53: 1 | K53: 22 | L53: Debit Card | M53: Delivered | N53: FedEx | O53: =_xlfn.XLOOKUP(G53,ProductMaster!$A$2:$A$23,ProductMaster!$C$2:$C$23,"Not Found") -> Books | P53: =IF(M53="Cancelled","Cancelled",IF(M53="delivered","Delivered","Active")) -> Delivered | Q53: =IF(M53="delivered",D53-B53,"") -> 2 | R53: =IF(M53="Delivered",IF(D53-B53<=2,"Fast","Slow"),"Not Delivered") -> Fast | S53: =IF(M53="delivered",K53,0) -> 22 | T53: =_xlfn.XLOOKUP(F53,CustomerMaster!$A$2:$A$50,CustomerMaster!$B$2:$B$50,"Not Found") -> Harper Young
A54: ORD0053 | B54: 12/29/2023 | C54: =TEXT(B54,"mmm") -> Dec | D54: 1/1/2024 | F54: CUST011 | G54: PROD016 | H54: Central | I54: 218 | J54: 5 | K54: 1090 | L54: PayPal | M54: Delivered | N54: DHL | O54: =_xlfn.XLOOKUP(G54,ProductMaster!$A$2:$A$23,ProductMaster!$C$2:$C$23,"Not Found") -> Home | P54: =IF(M54="Cancelled","Cancelled",IF(M54="delivered","Delivered","Active")) -> Delivered | Q54: =IF(M54="delivered",D54-B54,"") -> 3 | R54: =IF(M54="Delivered",IF(D54-B54<=2,"Fast","Slow"),"Not Delivered") -> Slow | S54: =IF(M54="delivered",K54,0) -> 1090 | T54: =_xlfn.XLOOKUP(F54,CustomerMaster!$A$2:$A$50,CustomerMaster!$B$2:$B$50,"Not Found") -> Mason Hall
A55: ORD0054 | B55: 3/6/2023 | C55: =TEXT(B55,"mmm") -> Mar | E55: 3/13/2023 | F55: CUST018 | G55: PROD004 | H55: North | I55: 64 | J55: 1 | K55: 64 | L55: Apple Pay | M55: Cancelled | N55: USPS | O55: =_xlfn.XLOOKUP(G55,ProductMaster!$A$2:$A$23,ProductMaster!$C$2:$C$23,"Not Found") -> Toys | P55: =IF(M55="Cancelled","Cancelled",IF(M55="delivered","Delivered","Active")) -> Cancelled | Q55: =IF(M55="delivered",D55-B55,"") | R55: =IF(M55="Delivered",IF(D55-B55<=2,"Fast","Slow"),"Not Delivered") -> Not Delivered | S55: =IF(M55="delivered",K55,0) -> 0 | T55: =_xlfn.XLOOKUP(F55,CustomerMaster!$A$2:$A$50,CustomerMaster!$B$2:$B$50,"Not Found") -> Grace Scott
A56: ORD0055 | B56: 2/2/2023 | C56: =TEXT(B56,"mmm") -> Feb | D56: 2/6/2023 | F56: CUST037 | G56: PROD021 | H56: Central | I56: 36 | J56: 4 | K56: 144 | L56: PayPal | M56: Delivered | N56: Amazon Logistics | O56: =_xlfn.XLOOKUP(G56,ProductMaster!$A$2:$A$23,ProductMaster!$C$2:$C$23,"Not Found") -> Home | P56: =IF(M56="Cancelled","Cancelled",IF(M56="delivered","Delivered","Active")) -> Delivered | Q56: =IF(M56="delivered",D56-B56,"") -> 4 | R56: =IF(M56="Delivered",IF(D56-B56<=2,"Fast","Slow"),"Not Delivered") -> Slow | S56: =IF(M56="delivered",K56,0) -> 144 | T56: =_xlfn.XLOOKUP(F56,CustomerMaster!$A$2:$A$50,CustomerMaster!$B$2:$B$50,"Not Found") -> Emily Johnson
A57: ORD0056 | B57: 10/18/2023 | C57: =TEXT(B57,"mmm") -> Oct | D57: 10/21/2023 | F57: CUST017 | G57: PROD004 | H57: West | I57: 65 | J57: 1 | K57: 65 | L57: Amazon Pay | M57: Delivered | N57: FedEx | O57: =_xlfn.XLOOKUP(G57,ProductMaster!$A$2:$A$23,ProductMaster!$C$2:$C$23,"Not Found") -> Toys | P57: =IF(M57="Cancelled","Cancelled",IF(M57="delivered","Delivered","Active")) -> Delivered | Q57: =IF(M57="delivered",D57-B57,"") -> 3 | R57: =IF(M57="Delivered",IF(D57-B57<=2,"Fast","Slow"),"Not Delivered") -> Slow | S57: =IF(M57="delivered",K57,0) -> 65 | T57: =_xlfn.XLOOKUP(F57,CustomerMaster!$A$2:$A$50,CustomerMaster!$B$2:$B$50,"Not Found") -> Emma King
A58: ORD0057 | B58: 1/7/2023 | C58: =TEXT(B58,"mmm") -> Jan | D58: 1/9/2023 | F58: CUST025 | G58: PROD005 | H58: Central | I58: 26 | J58: 1 | K58: 26 | L58: Apple Pay | M58: Delivered | N58: DHL | O58: =_xlfn.XLOOKUP(G58,ProductMaster!$A$2:$A$23,ProductMaster!$C$2:$C$23,"Not Found") -> Fashion | P58: =IF(M58="Cancelled","Cancelled",IF(M58="delivered","Delivered","Active")) -> Delivered | Q58: =IF(M58="delivered",D58-B58,"") -> 2 | R58: =IF(M58="Delivered",IF(D58-B58<=2,"Fast","Slow"),"Not Delivered") -> Fast | S58: =IF(M58="delivered",K58,0) -> 26 | T58: =_xlfn.XLOOKUP(F58,CustomerMaster!$A$2:$A$50,CustomerMaster!$B$2:$B$50,"Not Found") -> Emma King
A59: ORD0058 | B59: 5/8/2023 | C59: =TEXT(B59,"mmm") -> May | F59: CUST021 | G59: PROD009 | H59: North | I59: 11 | J59: 5 | K59: 55 | L59: Credit Card | M59: In Transit | N59: FedEx | O59: =_xlfn.XLOOKUP(G59,ProductMaster!$A$2:$A$23,ProductMaster!$C$2:$C$23,"Not Found") -> Books | P59: =IF(M59="Cancelled","Cancelled",IF(M59="delivered","Delivered","Active")) -> Active | Q59: =IF(M59="delivered",D59-B59,"") | R59: =IF(M59="Delivered",IF(D59-B59<=2,"Fast","Slow"),"Not Delivered") -> Not Delivered | S59: =IF(M59="delivered",K59,0) -> 0 | T59: =_xlfn.XLOOKUP(F59,CustomerMaster!$A$2:$A$50,CustomerMaster!$B$2:$B$50,"Not Found") -> Zoe Mitchell
A60: ORD0059 | B60: 4/2/2023 | C60: =TEXT(B60,"mmm") -> Apr | E60: 4/5/2023 | F60: CUST003 | G60: PROD013 | H60: North | I60: 195 | J60: 4 | K60: 195 | L60: PayPal | M60: Cancelled | N60: FedEx | O60: =_xlfn.XLOOKUP(G60,ProductMaster!$A$2:$A$23,ProductMaster!$C$2:$C$23,"Not Found") -> Home | P60: =IF(M60="Cancelled","Cancelled",IF(M60="delivered","Delivered","Active")) -> Cancelled | Q60: =IF(M60="delivered",D60-B60,"") | R60: =IF(M60="Delivered",IF(D60-B60<=2,"Fast","Slow"),"Not Delivered") -> Not Delivered | S60: =IF(M60="delivered",K60,0) -> 0 | T60: =_xlfn.XLOOKUP(F60,CustomerMaster!$A$2:$A$50,CustomerMaster!$B$2:$B$50,"Not Found") -> Ethan Davis
A61: ORD0060 | B61: 10/11/2023 | C61: =TEXT(B61,"mmm") -> Oct | E61: 10/12/2023 | F61: CUST019 | G61: PROD019 | H61: West | I61: 44 | J61: 5 | K61: 44 | L61: Apple Pay | M61: Cancelled | N61: USPS | O61: =_xlfn.XLOOKUP(G61,ProductMaster!$A$2:$A$23,ProductMaster!$C$2:$C$23,"Not Found") -> Fashion | P61: =IF(M61="Cancelled","Cancelled",IF(M61="delivered","Delivered","Active")) -> Cancelled | Q61: =IF(M61="delivered",D61-B61,"") | R61: =IF(M61="Delivered",IF(D61-B61<=2,"Fast","Slow"),"Not Delivered") -> Not Delivered | S61: =IF(M61="delivered",K61,0) -> 0 | T61: =_xlfn.XLOOKUP(F61,CustomerMaster!$A$2:$A$50,CustomerMaster!$B$2:$B$50,"Not Found") -> Ava Robinson
A62: ORD0061 | B62: 9/10/2023 | C62: =TEXT(B62,"mmm") -> Sep | F62: CUST035 | G62: PROD008 | H62: East | I62: 69 | J62: 4 | K62: 276 | L62: Debit Card | M62: In Transit | N62: DHL | O62: =_xlfn.XLOOKUP(G62,ProductMaster!$A$2:$A$23,ProductMaster!$C$2:$C$23,"Not Found") -> Books | P62: =IF(M62="Cancelled","Cancelled",IF(M62="delivered","Delivered","Active")) -> Active | Q62: =IF(M62="delivered",D62-B62,"") | R62: =IF(M62="Delivered",IF(D62-B62<=2,"Fast","Slow"),"Not Delivered") -> Not Delivered | S62: =IF(M62="delivered",K62,0) -> 0 | T62: =_xlfn.XLOOKUP(F62,CustomerMaster!$A$2:$A$50,CustomerMaster!$B$2:$B$50,"Not Found") -> Scarlett Adams
A63: ORD0062 | B63: 11/22/2023 | C63: =TEXT(B63,"mmm") -> Nov | D63: 11/29/2023 | F63: CUST022 | G63: PROD001 | H63: North | I63: 815 | J63: 4 | K63: 3260 | L63: Credit Card | M63: Delivered | N63: USPS | O63: =_xlfn.XLOOKUP(G63,ProductMaster!$A$2:$A$23,ProductMaster!$C$2:$C$23,"Not Found") -> Electronics | P63: =IF(M63="Cancelled","Cancelled",IF(M63="delivered","Delivered","Active")) -> Delivered | Q63: =IF(M63="delivered",D63-B63,"") -> 7 | R63: =IF(M63="Delivered",IF(D63-B63<=2,"Fast","Slow"),"Not Delivered") -> Slow | S63: =IF(M63="delivered",K63,0) -> 3260 | T63: =_xlfn.XLOOKUP(F63,CustomerMaster!$A$2:$A$50,CustomerMaster!$B$2:$B$50,"Not Found") -> Elijah Lewis
A64: ORD0063 | B64: 5/2/2023 | C64: =TEXT(B64,"mmm") -> May | F64: CUST004 | G64: PROD005 | H64: East | I64: 27 | J64: 1 | K64: 27 | L64: Debit Card | M64: In Transit | N64: Amazon Logistics | O64: =_xlfn.XLOOKUP(G64,ProductMaster!$A$2:$A$23,ProductMaster!$C$2:$C$23,"Not Found") -> Fashion | P64: =IF(M64="Cancelled","Cancelled",IF(M64="delivered","Delivered","Active")) -> Active | Q64: =IF(M64="delivered",D64-B64,"") | R64: =IF(M64="Delivered",IF(D64-B64<=2,"Fast","Slow"),"Not Delivered") -> Not Delivered | S64: =IF(M64="delivered",K64,0) -> 0 | T64: =_xlfn.XLOOKUP(F64,CustomerMaster!$A$2:$A$50,CustomerMaster!$B$2:$B$50,"Not Found") -> Noah Wilson
A65: ORD0064 | B65: 12/25/2023 | C65: =TEXT(B65,"mmm") -> Dec | D65: 12/29/2023 | F65: CUST048 | G65: PROD003 | H65: West | I65: 139 | J65: 5 | K65: 695 | L65: Apple Pay | M65: Delivered | N65: USPS | O65: =_xlfn.XLOOKUP(G65,ProductMaster!$A$2:$A$23,ProductMaster!$C$2:$C$23,"Not Found") -> Home | P65: =IF(M65="Cancelled","Cancelled",IF(M65="delivered","Delivered","Active")) -> Delivered | Q65: =IF(M65="delivered",D65-B65,"") -> 4 | R65: =IF(M65="Delivered",IF(D65-B65<=2,"Fast","Slow"),"Not Delivered") -> Slow | S65: =IF(M65="delivered",K65,0) -> 695 | T65: =_xlfn.XLOOKUP(F65,CustomerMaster!$A$2:$A$50,CustomerMaster!$B$2:$B$50,"Not Found") -> Noah Wilson
A66: ORD0065 | B66: 10/18/2023 | C66: =TEXT(B66,"mmm") -> Oct | E66: 10/20/2023 | F66: CUST009 | G66: PROD008 | H66: South | I66: 69 | J66: 3 | K66: 69 | L66: PayPal | M66: Cancelled | N66: Amazon Logistics | O66: =_xlfn.XLOOKUP(G66,ProductMaster!$A$2:$A$23,ProductMaster!$C$2:$C$23,"Not Found") -> Books | P66: =IF(M66="Cancelled","Cancelled",IF(M66="delivered","Delivered","Active")) -> Cancelled | Q66: =IF(M66="delivered",D66-B66,"") | R66: =IF(M66="Delivered",IF(D66-B66<=2,"Fast","Slow"),"Not Delivered") -> Not Delivered | S66: =IF(M66="delivered",K66,0) -> 0 | T66: =_xlfn.XLOOKUP(F66,CustomerMaster!$A$2:$A$50,CustomerMaster!$B$2:$B$50,"Not Found") -> Jackson Allen
A67: ORD0066 | B67: 5/20/2023 | C67: =TEXT(B67,"mmm") -> May | E67: 5/21/2023 | F67: CUST009 | G67: PROD019 | H67: West | I67: 42 | J67: 1 | K67: 42 | L67: Apple Pay | M67: Cancelled | N67: DHL | O67: =_xlfn.XLOOKUP(G67,ProductMaster!$A$2:$A$23,ProductMaster!$C$2:$C$23,"Not Found") -> Fashion | P67: =IF(M67="Cancelled","Cancelled",IF(M67="delivered","Delivered","Active")) -> Cancelled | Q67: =IF(M67="delivered",D67-B67,"") | R67: =IF(M67="Delivered",IF(D67-B67<=2,"Fast","Slow"),"Not Delivered") -> Not Delivered | S67: =IF(M67="delivered",K67,0) -> 0 | T67: =_xlfn.XLOOKUP(F67,CustomerMaster!$A$2:$A$50,CustomerMaster!$B$2:$B$50,"Not Found") -> Jackson Allen
A68: ORD0067 | B68: 7/28/2023 | C68: =TEXT(B68,"mmm") -> Jul | D68: 7/30/2023 | F68: CUST050 | G68: PROD007 | H68: North | I68: 31 | J68: 4 | K68: 124 | L68: Credit Card | M68: Delivered | N68: UPS | O68: =_xlfn.XLOOKUP(G68,ProductMaster!$A$2:$A$23,ProductMaster!$C$2:$C$23,"Not Found") -> Toys | P68: =IF(M68="Cancelled","Cancelled",IF(M68="delivered","Delivered","Active")) -> Delivered | Q68: =IF(M68="delivered",D68-B68,"") -> 2 | R68: =IF(M68="Delivered",IF(D68-B68<=2,"Fast","Slow"),"Not Delivered") -> Fast | S68: =IF(M68="delivered",K68,0) -> 124 | T68: =_xlfn.XLOOKUP(F68,CustomerMaster!$A$2:$A$50,CustomerMaster!$B$2:$B$50,"Not Found") -> Not Found
A69: ORD0068 | B69: 12/18/2023 | C69: =TEXT(B69,"mmm") -> Dec | F69: CUST045 | G69: PROD020 | H69: West | I69: 104 | J69: 3 | K69: 312 | L69: Credit Card | M69: In Transit | N69: UPS | O69: =_xlfn.XLOOKUP(G69,ProductMaster!$A$2:$A$23,ProductMaster!$C$2:$C$23,"Not Found") -> Electronics | P69: =IF(M69="Cancelled","Cancelled",IF(M69="delivered","Delivered","Active")) -> Active | Q69: =IF(M69="delivered",D69-B69,"") | R69: =IF(M69="Delivered",IF(D69-B69<=2,"Fast","Slow"),"Not Delivered") -> Not Delivered | S69: =IF(M69="delivered",K69,0) -> 0 | T69: =_xlfn.XLOOKUP(F69,CustomerMaster!$A$2:$A$50,CustomerMaster!$B$2:$B$50,"Not Found") -> Emily Johnson
A70: ORD0069 | B70: 7/2/2023 | C70: =TEXT(B70,"mmm") -> Jul | E70: 7/7/2023 | F70: CUST044 | G70: PROD010 | H70: East | I70: 58 | J70: 2 | K70: 58 | L70: Apple Pay | M70: Cancelled | N70: USPS | O70: =_xlfn.XLOOKUP(G70,ProductMaster!$A$2:$A$23,ProductMaster!$C$2:$C$23,"Not Found") -> Fashion | P70: =IF(M70="Cancelled","Cancelled",IF(M70="delivered","Delivered","Active")) -> Cancelled | Q70: =IF(M70="delivered",D70-B70,"") | R70: =IF(M70="Delivered",IF(D70-B70<=2,"Fast","Slow"),"Not Delivered") -> Not Delivered | S70: =IF(M70="delivered",K70,0) -> 0 | T70: =_xlfn.XLOOKUP(F70,CustomerMaster!$A$2:$A$50,CustomerMaster!$B$2:$B$50,"Not Found") -> Grace Ward
A71: ORD0070 | B71: 10/9/2023 | C71: =TEXT(B71,"mmm") -> Oct | E71: 10/10/2023 | F71: CUST009 | G71: PROD004 | H71: West | I71: 62 | J71: 2 | K71: 62 | L71: Debit Card | M71: Cancelled | N71: DHL | O71: =_xlfn.XLOOKUP(G71,ProductMaster!$A$2:$A$23,ProductMaster!$C$2:$C$23,"Not Found") -> Toys | P71: =IF(M71="Cancelled","Cancelled",IF(M71="delivered","Delivered","Active")) -> Cancelled | Q71: =IF(M71="delivered",D71-B71,"") | R71: =IF(M71="Delivered",IF(D71-B71<=2,"Fast","Slow"),"Not Delivered") -> Not Delivered | S71: =IF(M71="delivered",K71,0) -> 0 | T71: =_xlfn.XLOOKUP(F71,CustomerMaster!$A$2:$A$50,CustomerMaster!$B$2:$B$50,"Not Found") -> Jackson Allen
A72: ORD0071 | B72: 12/18/2023 | C72: =TEXT(B72,"mmm") -> Dec | D72: 12/25/2023 | F72: CUST006 | G72: PROD019 | H72: East | I72: 43 | J72: 1 | K72: 43 | L72: Credit Card | M72: Delivered | N72: Amazon Logistics | O72: =_xlfn.XLOOKUP(G72,ProductMaster!$A$2:$A$23,ProductMaster!$C$2:$C$23,"Not Found") -> Fashion | P72: =IF(M72="Cancelled","Cancelled",IF(M72="delivered","Delivered","Active")) -> Delivered | Q72: =IF(M72="delivered",D72-B72,"") -> 7 | R72: =IF(M72="Delivered",IF(D72-B72<=2,"Fast","Slow"),"Not Delivered") -> Slow | S72: =IF(M72="delivered",K72,0) -> 43 | T72: =_xlfn.XLOOKUP(F72,CustomerMaster!$A$2:$A$50,CustomerMaster!$B$2:$B$50,"Not Found") -> Ava Robinson
A73: ORD0072 | B73: 3/7/2023 | C73: =TEXT(B73,"mmm") -> Mar | F73: CUST022 | G73: PROD004 | H73: East | I73: 62 | J73: 4 | K73: 248 | L73: Debit Card | M73: In Transit | N73: Amazon Logistics | O73: =_xlfn.XLOOKUP(G73,ProductMaster!$A$2:$A$23,ProductMaster!$C$2:$C$23,"Not Found") -> Toys | P73: =IF(M73="Cancelled","Cancelled",IF(M73="delivered","Delivered","Active")) -> Active | Q73: =IF(M73="delivered",D73-B73,"") | R73: =IF(M73="Delivered",IF(D73-B73<=2,"Fast","Slow"),"Not Delivered") -> Not Delivered | S73: =IF(M73="delivered",K73,0) -> 0 | T73: =_xlfn.XLOOKUP(F73,CustomerMaster!$A$2:$A$50,CustomerMaster!$B$2:$B$50,"Not Found") -> Elijah Lewis
A74: ORD0073 | B74: 7/22/2023 | C74: =TEXT(B74,"mmm") -> Jul | E74: 7/25/2023 | F74: CUST028 | G74: PROD006 | H74: North | I74: 95 | J74: 2 | K74: 95 | L74: PayPal | M74: Cancelled | N74: UPS | O74: =_xlfn.XLOOKUP(G74,ProductMaster!$A$2:$A$23,ProductMaster!$C$2:$C$23,"Not Found") -> Fashion | P74: =IF(M74="Cancelled","Cancelled",IF(M74="delivered","Delivered","Active")) -> Cancelled | Q74: =IF(M74="delivered",D74-B74,"") | R74: =IF(M74="Delivered",IF(D74-B74<=2,"Fast","Slow"),"Not Delivered") -> Not Delivered | S74: =IF(M74="delivered",K74,0) -> 0 | T74: =_xlfn.XLOOKUP(F74,CustomerMaster!$A$2:$A$50,CustomerMaster!$B$2:$B$50,"Not Found") -> Lily Bennett
A75: ORD0074 | B75: 1/18/2023 | C75: =TEXT(B75,"mmm") -> Jan | D75: 1/24/2023 | F75: CUST016 | G75: PROD021 | H75: Central | I75: 36 | J75: 4 | K75: 144 | L75: Apple Pay | M75: Delivered | N75: FedEx | O75: =_xlfn.XLOOKUP(G75,ProductMaster!$A$2:$A$23,ProductMaster!$C$2:$C$23,"Not Found") -> Home | P75: =IF(M75="Cancelled","Cancelled",IF(M75="delivered","Delivered","Active")) -> Delivered | Q75: =IF(M75="delivered",D75-B75,"") -> 6 | R75: =IF(M75="Delivered",IF(D75-B75<=2,"Fast","Slow"),"Not Delivered") -> Slow | S75: =IF(M75="delivered",K75,0) -> 144 | T75: =_xlfn.XLOOKUP(F75,CustomerMaster!$A$2:$A$50,CustomerMaster!$B$2:$B$50,"Not Found") -> Elijah Lewis
A76: ORD0075 | B76: 5/24/2023 | C76: =TEXT(B76,"mmm") -> May | F76: CUST042 | G76: PROD017 | H76: East | I76: 73 | J76: 5 | K76: 365 | L76: Apple Pay | M76: In Transit | N76: DHL | O76: =_xlfn.XLOOKUP(G76,ProductMaster!$A$2:$A$23,ProductMaster!$C$2:$C$23,"Not Found") -> Electronics | P76: =IF(M76="Cancelled","Cancelled",IF(M76="delivered","Delivered","Active")) -> Active | Q76: =IF(M76="delivered",D76-B76,"") | R76: =IF(M76="Delivered",IF(D76-B76<=2,"Fast","Slow"),"Not Delivered") -> Not Delivered | S76: =IF(M76="delivered",K76,0) -> 0 | T76: =_xlfn.XLOOKUP(F76,CustomerMaster!$A$2:$A$50,CustomerMaster!$B$2:$B$50,"Not Found") -> Noah Wilson
A77: ORD0076 | B77: 9/3/2023 | C77: =TEXT(B77,"mmm") -> Sep | D77: 9/9/2023 | F77: CUST023 | G77: PROD019 | H77: North | I77: 43 | J77: 4 | K77: 172 | L77: Debit Card | M77: Delivered | N77: DHL | O77: =_xlfn.XLOOKUP(G77,ProductMaster!$A$2:$A$23,ProductMaster!$C$2:$C$23,"Not Found") -> Fashion | P77: =IF(M77="Cancelled","Cancelled",IF(M77="delivered","Delivered","Active")) -> Delivered | Q77: =IF(M77="delivered",D77-B77,"") -> 6 | R77: =IF(M77="Delivered",IF(D77-B77<=2,"Fast","Slow"),"Not Delivered") -> Slow | S77: =IF(M77="delivered",K77,0) -> 172 | T77: =_xlfn.XLOOKUP(F77,CustomerMaster!$A$2:$A$50,CustomerMaster!$B$2:$B$50,"Not Found") -> Charlotte Reed
A78: ORD0077 | B78: 11/2/2023 | C78: =TEXT(B78,"mmm") -> Nov | D78: 11/4/2023 | F78: CUST004 | G78: PROD016 | H78: West | I78: 214 | J78: 5 | K78: 1070 | L78: Debit Card | M78: Delivered | N78: UPS | O78: =_xlfn.XLOOKUP(G78,ProductMaster!$A$2:$A$23,ProductMaster!$C$2:$C$23,"Not Found") -> Home | P78: =IF(M78="Cancelled","Cancelled",IF(M78="delivered","Delivered","Active")) -> Delivered | Q78: =IF(M78="delivered",D78-B78,"") -> 2 | R78: =IF(M78="Delivered",IF(D78-B78<=2,"Fast","Slow"),"Not Delivered") -> Fast | S78: =IF(M78="delivered",K78,0) -> 1070 | T78: =_xlfn.XLOOKUP(F78,CustomerMaster!$A$2:$A$50,CustomerMaster!$B$2:$B$50,"Not Found") -> Noah Wilson
A79: ORD0078 | B79: 12/3/2023 | C79: =TEXT(B79,"mmm") -> Dec | E79: 12/6/2023 | F79: CUST048 | G79: PROD002 | H79: Central | I79: 42 | J79: 2 | K79: 42 | L79: Apple Pay | M79: Cancelled | N79: UPS | O79: =_xlfn.XLOOKUP(G79,ProductMaster!$A$2:$A$23,ProductMaster!$C$2:$C$23,"Not Found") -> Toys | P79: =IF(M79="Cancelled","Cancelled",IF(M79="delivered","Delivered","Active")) -> Cancelled | Q79: =IF(M79="delivered",D79-B79,"") | R79: =IF(M79="Delivered",IF(D79-B79<=2,"Fast","Slow"),"Not Delivered") -> Not Delivered | S79: =IF(M79="delivered",K79,0) -> 0 | T79: =_xlfn.XLOOKUP(F79,CustomerMaster!$A$2:$A$50,CustomerMaster!$B$2:$B$50,"Not Found") -> Noah Wilson
A80: ORD0079 | B80: 4/1/2023 | C80: =TEXT(B80,"mmm") -> Apr | F80: CUST048 | G80: PROD012 | H80: North | I80: 46 | J80: 1 | K80: 46 | L80: Amazon Pay | M80: In Transit | N80: UPS | O80: =_xlfn.XLOOKUP(G80,ProductMaster!$A$2:$A$23,ProductMaster!$C$2:$C$23,"Not Found") -> Home | P80: =IF(M80="Cancelled","Cancelled",IF(M80="delivered","Delivered","Active")) -> Active | Q80: =IF(M80="delivered",D80-B80,"") | R80: =IF(M80="Delivered",IF(D80-B80<=2,"Fast","Slow"),"Not Delivered") -> Not Delivered | S80: =IF(M80="delivered",K80,0) -> 0 | T80: =_xlfn.XLOOKUP(F80,CustomerMaster!$A$2:$A$50,CustomerMaster!$B$2:$B$50,"Not Found") -> Noah Wilson
A81: ORD0080 | B81: 10/16/2023 | C81: =TEXT(B81,"mmm") -> Oct | D81: 10/19/2023 | F81: CUST032 | G81: PROD018 | H81: East | I81: 95 | J81: 4 | K81: 380 | L81: Credit Card | M81: Delivered | N81: UPS | O81: =_xlfn.XLOOKUP(G81,ProductMaster!$A$2:$A$23,ProductMaster!$C$2:$C$23,"Not Found") -> Toys | P81: =IF(M81="Cancelled","Cancelled",IF(M81="delivered","Delivered","Active")) -> Delivered | Q81: =IF(M81="delivered",D81-B81,"") -> 3 | R81: =IF(M81="Delivered",IF(D81-B81<=2,"Fast","Slow"),"Not Delivered") -> Slow | S81: =IF(M81="delivered",K81,0) -> 380 | T81: =_xlfn.XLOOKUP(F81,CustomerMaster!$A$2:$A$50,CustomerMaster!$B$2:$B$50,"Not Found") -> Luke Gray
A82: ORD0081 | B82: 11/5/2023 | C82: =TEXT(B82,"mmm") -> Nov | F82: CUST001 | G82: PROD011 | H82: West | I82: 174 | J82: 2 | K82: 348 | L82: PayPal | M82: In Transit | N82: UPS | O82: =_xlfn.XLOOKUP(G82,ProductMaster!$A$2:$A$23,ProductMaster!$C$2:$C$23,"Not Found") -> Electronics | P82: =IF(M82="Cancelled","Cancelled",IF(M82="delivered","Delivered","Active")) -> Active | Q82: =IF(M82="delivered",D82-B82,"") | R82: =IF(M82="Delivered",IF(D82-B82<=2,"Fast","Slow"),"Not Delivered") -> Not Delivered | S82: =IF(M82="delivered",K82,0) -> 0 | T82: =_xlfn.XLOOKUP(F82,CustomerMaster!$A$2:$A$50,CustomerMaster!$B$2:$B$50,"Not Found") -> James Miller
A83: ORD0082 | B83: 6/15/2023 | C83: =TEXT(B83,"mmm") -> Jun | E83: 6/18/2023 | F83: CUST046 | G83: PROD005 | H83: North | I83: 27 | J83: 5 | K83: 27 | L83: Credit Card | M83: Cancelled | N83: Amazon Logistics | O83: =_xlfn.XLOOKUP(G83,ProductMaster!$A$2:$A$23,ProductMaster!$C$2:$C$23,"Not Found") -> Fashion | P83: =IF(M83="Cancelled","Cancelled",IF(M83="delivered","Delivered","Active")) -> Cancelled | Q83: =IF(M83="delivered",D83-B83,"") | R83: =IF(M83="Delivered",IF(D83-B83<=2,"Fast","Slow"),"Not Delivered") -> Not Delivered | S83: =IF(M83="delivered",K83,0) -> 0 | T83: =_xlfn.XLOOKUP(F83,CustomerMaster!$A$2:$A$50,CustomerMaster!$B$2:$B$50,"Not Found") -> Emily Johnson
A84: ORD0083 | B84: 10/28/2023 | C84: =TEXT(B84,"mmm") -> Oct | D84: 10/30/2023 | F84: CUST021 | G84: PROD005 | H84: South | I84: 27 | J84: 4 | K84: 108 | L84: PayPal | M84: Delivered | N84: USPS | O84: =_xlfn.XLOOKUP(G84,ProductMaster!$A$2:$A$23,ProductMaster!$C$2:$C$23,"Not Found") -> Fashion | P84: =IF(M84="Cancelled","Cancelled",IF(M84="delivered","Delivered","Active")) -> Delivered | Q84: =IF(M84="delivered",D84-B84,"") -> 2 | R84: =IF(M84="Delivered",IF(D84-B84<=2,"Fast","Slow"),"Not Delivered") -> Fast | S84: =IF(M84="delivered",K84,0) -> 108 | T84: =_xlfn.XLOOKUP(F84,CustomerMaster!$A$2:$A$50,CustomerMaster!$B$2:$B$50,"Not Found") -> Zoe Mitchell
A85: ORD0084 | B85: 12/22/2023 | C85: =TEXT(B85,"mmm") -> Dec | F85: CUST015 | G85: PROD022 | H85: South | I85: 65 | J85: 2 | K85: 130 | L85: PayPal | M85: In Transit | N85: DHL | O85: =_xlfn.XLOOKUP(G85,ProductMaster!$A$2:$A$23,ProductMaster!$C$2:$C$23,"Not Found") -> Fashion | P85: =IF(M85="Cancelled","Cancelled",IF(M85="delivered","Delivered","Active")) -> Active | Q85: =IF(M85="delivered",D85-B85,"") | R85: =IF(M85="Delivered",IF(D85-B85<=2,"Fast","Slow"),"Not Delivered") -> Not Delivered | S85: =IF(M85="delivered",K85,0) -> 0 | T85: =_xlfn.XLOOKUP(F85,CustomerMaster!$A$2:$A$50,CustomerMaster!$B$2:$B$50,"Not Found") -> Ava White
A86: ORD0085 | B86: 3/7/2023 | C86: =TEXT(B86,"mmm") -> Mar | F86: CUST045 | G86: PROD019 | H86: East | I86: 43 | J86: 5 | K86: 215 | L86: Debit Card | M86: In Transit | N86: DHL | O86: =_xlfn.XLOOKUP(G86,ProductMaster!$A$2:$A$23,ProductMaster!$C$2:$C$23,"Not Found") -> Fashion | P86: =IF(M86="Cancelled","Cancelled",IF(M86="delivered","Delivered","Active")) -> Active | Q86: =IF(M86="delivered",D86-B86,"") | R86: =IF(M86="Delivered",IF(D86-B86<=2,"Fast","Slow"),"Not Delivered") -> Not Delivered | S86: =IF(M86="delivered",K86,0) -> 0 | T86: =_xlfn.XLOOKUP(F86,CustomerMaster!$A$2:$A$50,CustomerMaster!$B$2:$B$50,"Not Found") -> Emily Johnson
A87: ORD0086 | B87: 11/10/2023 | C87: =TEXT(B87,"mmm") -> Nov | F87: CUST007 | G87: PROD016 | H87: West | I87: 210 | J87: 1 | K87: 210 | L87: PayPal | M87: In Transit | N87: UPS | O87: =_xlfn.XLOOKUP(G87,ProductMaster!$A$2:$A$23,ProductMaster!$C$2:$C$23,"Not Found") -> Home | P87: =IF(M87="Cancelled","Cancelled",IF(M87="delivered","Delivered","Active")) -> Active | Q87: =IF(M87="delivered",D87-B87,"") | R87: =IF(M87="Delivered",IF(D87-B87<=2,"Fast","Slow"),"Not Delivered") -> Not Delivered | S87: =IF(M87="delivered",K87,0) -> 0 | T87: =_xlfn.XLOOKUP(F87,CustomerMaster!$A$2:$A$50,CustomerMaster!$B$2:$B$50,"Not Found") -> Liam Walker
A88: ORD0087 | B88: 11/22/2023 | C88: =TEXT(B88,"mmm") -> Nov | F88: CUST043 | G88: PROD021 | H88: South | I88: 37 | J88: 3 | K88: 111 | L88: Credit Card | M88: In Transit | N88: UPS | O88: =_xlfn.XLOOKUP(G88,ProductMaster!$A$2:$A$23,ProductMaster!$C$2:$C$23,"Not Found") -> Home | P88: =IF(M88="Cancelled","Cancelled",IF(M88="delivered","Delivered","Active")) -> Active | Q88: =IF(M88="delivered",D88-B88,"") | R88: =IF(M88="Delivered",IF(D88-B88<=2,"Fast","Slow"),"Not Delivered") -> Not Delivered | S88: =IF(M88="delivered",K88,0) -> 0 | T88: =_xlfn.XLOOKUP(F88,CustomerMaster!$A$2:$A$50,CustomerMaster!$B$2:$B$50,"Not Found") -> Lily Reed
A89: ORD0088 | B89: 5/8/2023 | C89: =TEXT(B89,"mmm") -> May | F89: CUST007 | G89: PROD001 | H89: South | I89: 788 | J89: 4 | K89: 3152 | L89: Debit Card | M89: In Transit | N89: Amazon Logistics | O89: =_xlfn.XLOOKUP(G89,ProductMaster!$A$2:$A$23,ProductMaster!$C$2:$C$23,"Not Found") -> Electronics | P89: =IF(M89="Cancelled","Cancelled",IF(M89="delivered","Delivered","Active")) -> Active | Q89: =IF(M89="delivered",D89-B89,"") | R89: =IF(M89="Delivered",IF(D89-B89<=2,"Fast","Slow"),"Not Delivered") -> Not Delivered | S89: =IF(M89="delivered",K89,0) -> 0 | T89: =_xlfn.XLOOKUP(F89,CustomerMaster!$A$2:$A$50,CustomerMaster!$B$2:$B$50,"Not Found") -> Liam Walker
A90: ORD0089 | B90: 7/13/2023 | C90: =TEXT(B90,"mmm") -> Jul | F90: CUST007 | G90: PROD016 | H90: West | I90: 217 | J90: 5 | K90: 1085 | L90: Debit Card | M90: In Transit | N90: FedEx | O90: =_xlfn.XLOOKUP(G90,ProductMaster!$A$2:$A$23,ProductMaster!$C$2:$C$23,"Not Found") -> Home | P90: =IF(M90="Cancelled","Cancelled",IF(M90="delivered","Delivered","Active")) -> Active | Q90: =IF(M90="delivered",D90-B90,"") | R90: =IF(M90="Delivered",IF(D90-B90<=2,"Fast","Slow"),"Not Delivered") -> Not Delivered | S90: =IF(M90="delivered",K90,0) -> 0 | T90: =_xlfn.XLOOKUP(F90,CustomerMaster!$A$2:$A$50,CustomerMaster!$B$2:$B$50,"Not Found") -> Liam Walker
A91: ORD0090 | B91: 1/18/2023 | C91: =TEXT(B91,"mmm") -> Jan | F91: CUST007 | G91: PROD003 | H91: West | I91: 138 | J91: 4 | K91: 552 | L91: Credit Card | M91: In Transit | N91: FedEx | O91: =_xlfn.XLOOKUP(G91,ProductMaster!$A$2:$A$23,ProductMaster!$C$2:$C$23,"Not Found") -> Home | P91: =IF(M91="Cancelled","Cancelled",IF(M91="delivered","Delivered","Active")) -> Active | Q91: =IF(M91="delivered",D91-B91,"") | R91: =IF(M91="Delivered",IF(D91-B91<=2,"Fast","Slow"),"Not Delivered") -> Not Delivered | S91: =IF(M91="delivered",K91,0) -> 0 | T91: =_xlfn.XLOOKUP(F91,CustomerMaster!$A$2:$A$50,CustomerMaster!$B$2:$B$50,"Not Found") -> Liam Walker
A92: ORD0091 | B92: 6/23/2023 | C92: =TEXT(B92,"mmm") -> Jun | D92: 6/29/2023 | F92: CUST031 | G92: PROD001 | H92: Central | I92: 803 | J92: 2 | K92: 1606 | L92: Apple Pay | M92: Delivered | N92: FedEx | O92: =_xlfn.XLOOKUP(G92,ProductMaster!$A$2:$A$23,ProductMaster!$C$2:$C$23,"Not Found") -> Electronics | P92: =IF(M92="Cancelled","Cancelled",IF(M92="delivered","Delivered","Active")) -> Delivered | Q92: =IF(M92="delivered",D92-B92,"") -> 6 | R92: =IF(M92="Delivered",IF(D92-B92<=2,"Fast","Slow"),"Not Delivered") -> Slow | S92: =IF(M92="delivered",K92,0) -> 1606 | T92: =_xlfn.XLOOKUP(F92,CustomerMaster!$A$2:$A$50,CustomerMaster!$B$2:$B$50,"Not Found") -> Mason Collins
A93: ORD0092 | B93: 2/21/2023 | C93: =TEXT(B93,"mmm") -> Feb | E93: 2/25/2023 | F93: CUST013 | G93: PROD014 | H93: North | I93: 248 | J93: 5 | K93: 248 | L93: PayPal | M93: Cancelled | N93: UPS | O93: =_xlfn.XLOOKUP(G93,ProductMaster!$A$2:$A$23,ProductMaster!$C$2:$C$23,"Not Found") -> Electronics | P93: =IF(M93="Cancelled","Cancelled",IF(M93="delivered","Delivered","Active")) -> Cancelled | Q93: =IF(M93="delivered",D93-B93,"") | R93: =IF(M93="Delivered",IF(D93-B93<=2,"Fast","Slow"),"Not Delivered") -> Not Delivered | S93: =IF(M93="delivered",K93,0) -> 0 | T93: =_xlfn.XLOOKUP(F93,CustomerMaster!$A$2:$A$50,CustomerMaster!$B$2:$B$50,"Not Found") -> Olivia Martinez
A94: ORD0093 | B94: 2/19/2023 | C94: =TEXT(B94,"mmm") -> Feb | D94: 2/21/2023 | F94: CUST036 | G94: PROD016 | H94: East | I94: 210 | J94: 3 | K94: 630 | L94: Apple Pay | M94: Delivered | N94: DHL | O94: =_xlfn.XLOOKUP(G94,ProductMaster!$A$2:$A$23,ProductMaster!$C$2:$C$23,"Not Found") -> Home | P94: =IF(M94="Cancelled","Cancelled",IF(M94="delivered","Delivered","Active")) -> Delivered | Q94: =IF(M94="delivered",D94-B94,"") -> 2 | R94: =IF(M94="Delivered",IF(D94-B94<=2,"Fast","Slow"),"Not Delivered") -> Fast | S94: =IF(M94="delivered",K94,0) -> 630 | T94: =_xlfn.XLOOKUP(F94,CustomerMaster!$A$2:$A$50,CustomerMaster!$B$2:$B$50,"Not Found") -> Ethan Davis
A95: ORD0094 | B95: 12/5/2023 | C95: =TEXT(B95,"mmm") -> Dec | E95: 12/12/2023 | F95: CUST013 | G95: PROD004 | H95: North | I95: 62 | J95: 2 | K95: 62 | L95: Credit Card | M95: Cancelled | N95: FedEx | O95: =_xlfn.XLOOKUP(G95,ProductMaster!$A$2:$A$23,ProductMaster!$C$2:$C$23,"Not Found") -> Toys | P95: =IF(M95="Cancelled","Cancelled",IF(M95="delivered","Delivered","Active")) -> Cancelled | Q95: =IF(M95="delivered",D95-B95,"") | R95: =IF(M95="Delivered",IF(D95-B95<=2,"Fast","Slow"),"Not Delivered") -> Not Delivered | S95: =IF(M95="delivered",K95,0) -> 0 | T95: =_xlfn.XLOOKUP(F95,CustomerMaster!$A$2:$A$50,CustomerMaster!$B$2:$B$50,"Not Found") -> Olivia Martinez
A96: ORD0095 | B96: 6/7/2023 | C96: =TEXT(B96,"mmm") -> Jun | E96: 6/12/2023 | F96: CUST043 | G96: PROD009 | H96: South | I96: 11 | J96: 5 | K96: 11 | L96: Debit Card | M96: Cancelled | N96: Amazon Logistics | O96: =_xlfn.XLOOKUP(G96,ProductMaster!$A$2:$A$23,ProductMaster!$C$2:$C$23,"Not Found") -> Books | P96: =IF(M96="Cancelled","Cancelled",IF(M96="delivered","Delivered","Active")) -> Cancelled | Q96: =IF(M96="delivered",D96-B96,"") | R96: =IF(M96="Delivered",IF(D96-B96<=2,"Fast","Slow"),"Not Delivered") -> Not Delivered | S96: =IF(M96="delivered",K96,0) -> 0 | T96: =_xlfn.XLOOKUP(F96,CustomerMaster!$A$2:$A$50,CustomerMaster!$B$2:$B$50,"Not Found") -> Lily Reed
A97: ORD0096 | B97: 7/9/2023 | C97: =TEXT(B97,"mmm") -> Jul | D97: 7/12/2023 | F97: CUST017 | G97: PROD015 | H97: North | I97: 21 | J97: 2 | K97: 42 | L97: Amazon Pay | M97: Delivered | N97: UPS | O97: =_xlfn.XLOOKUP(G97,ProductMaster!$A$2:$A$23,ProductMaster!$C$2:$C$23,"Not Found") -> Books | P97: =IF(M97="Cancelled","Cancelled",IF(M97="delivered","Delivered","Active")) -> Delivered | Q97: =IF(M97="delivered",D97-B97,"") -> 3 | R97: =IF(M97="Delivered",IF(D97-B97<=2,"Fast","Slow"),"Not Delivered") -> Slow | S97: =IF(M97="delivered",K97,0) -> 42 | T97: =_xlfn.XLOOKUP(F97,CustomerMaster!$A$2:$A$50,CustomerMaster!$B$2:$B$50,"Not Found") -> Emma King
A98: ORD0097 | B98: 12/23/2023 | C98: =TEXT(B98,"mmm") -> Dec | D98: 12/26/2023 | F98: CUST023 | G98: PROD018 | H98: West | I98: 95 | J98: 5 | K98: 475 | L98: Amazon Pay | M98: Delivered | N98: Amazon Logistics | O98: =_xlfn.XLOOKUP(G98,ProductMaster!$A$2:$A$23,ProductMaster!$C$2:$C$23,"Not Found") -> Toys | P98: =IF(M98="Cancelled","Cancelled",IF(M98="delivered","Delivered","Active")) -> Delivered | Q98: =IF(M98="delivered",D98-B98,"") -> 3 | R98: =IF(M98="Delivered",IF(D98-B98<=2,"Fast","Slow"),"Not Delivered") -> Slow | S98: =IF(M98="delivered",K98,0) -> 475 | T98: =_xlfn.XLOOKUP(F98,CustomerMaster!$A$2:$A$50,CustomerMaster!$B$2:$B$50,"Not Found") -> Charlotte Reed
A99: ORD0098 | B99: 9/25/2023 | C99: =TEXT(B99,"mmm") -> Sep | D99: 9/30/2023 | F99: CUST044 | G99: PROD016 | H99: South | I99: 215 | J99: 2 | K99: 430 | L99: PayPal | M99: Delivered | N99: Amazon Logistics | O99: =_xlfn.XLOOKUP(G99,ProductMaster!$A$2:$A$23,ProductMaster!$C$2:$C$23,"Not Found") -> Home | P99: =IF(M99="Cancelled","Cancelled",IF(M99="delivered","Delivered","Active")) -> Delivered | Q99: =IF(M99="delivered",D99-B99,"") -> 5 | R99: =IF(M99="Delivered",IF(D99-B99<=2,"Fast","Slow"),"Not Delivered") -> Slow | S99: =IF(M99="delivered",K99,0) -> 430 | T99: =_xlfn.XLOOKUP(F99,CustomerMaster!$A$2:$A$50,CustomerMaster!$B$2:$B$50,"Not Found") -> Grace Ward
A100: ORD0099 | B100: 1/18/2023 | C100: =TEXT(B100,"mmm") -> Jan | E100: 1/24/2023 | F100: CUST034 | G100: PROD019 | H100: West | I100: 43 | J100: 5 | K100: 43 | L100: Credit Card | M100: Cancelled | N100: UPS | O100: =_xlfn.XLOOKUP(G100,ProductMaster!$A$2:$A$23,ProductMaster!$C$2:$C$23,"Not Found") -> Fashion | P100: =IF(M100="Cancelled","Cancelled",IF(M100="delivered","Delivered","Active")) -> Cancelled | Q100: =IF(M100="delivered",D100-B100,"") | R100: =IF(M100="Delivered",IF(D100-B100<=2,"Fast","Slow"),"Not Delivered") -> Not Delivered | S100: =IF(M100="delivered",K100,0) -> 0 | T100: =_xlfn.XLOOKUP(F100,CustomerMaster!$A$2:$A$50,CustomerMaster!$B$2:$B$50,"Not Found") -> Lily Simmons
...

Sheet Sheet2
L3: Row Labels | M3: Sum of Effective Sales
B4: Row Labels | C4: Count of Order Status | H4: Row Labels | I4: Sum of Effective Sales | L4: Central | M4: 3010
B5: Cancelled | C5: 30 | H5: Books | I5: 127 | L5: East | M5: 1842
B6: Delivered | C6: 34 | H6: Electronics | I6: 6126 | L6: North | M6: 4075
H7: Fashion | I7: 1376 | L7: South | M7: 1063
H8: Home | I8: 4203 | L8: West | M8: 3666
H9: Toys | I9: 1824
B16: Row Labels | C16: Sum of Effective Sales | I16: Row Labels | J16: Sum of Effective Sales
B17: Amazon Logistics | C17: 2234 | I17: Apr | J17: 0
B18: DHL | C18: 2365 | I18: Aug | J18: 0
B19: FedEx | C19: 1934 | I19: Dec | J19: 2767
B20: UPS | C20: 2578 | I20: Feb | J20: 1298
B21: USPS | C21: 4545 | I21: Jan | J21: 192
I22: Jul | J22: 459
I23: Jun | J23: 1669
I24: Mar | J24: 0
I25: May | J25: 97
I26: Nov | J26: 4810
I27: Oct | J27: 1070
I28: Sep | J28: 1294

Sheet PivotTable
A1: Payment Method | B1: (All)
A3: Row Labels | B3: Sum of Sales Amount | D3: Row Labels | E3: Average of Delivery Days | K3: Sum of Effective Sales | L3: Product Category
A4: Central | B4: 4656 | D4: Central | E4: 4.2 | K4: Row Labels | L4: Books | M4: Electronics | N4: Fashion | O4: Home | P4: Toys | Q4: Grand Total
A5: Books | B5: 84 | D5: East | E5: 4.25 | K5: Jan | L5: 22 | N5: 26 | O5: 144 | Q5: 192
A6: Electronics | B6: 2452 | D6: North | E6: 3.625 | K6: Feb | L6: 0 | M6: 0 | N6: 140 | O6: 774 | P6: 384 | Q6: 1298
A7: Fashion | B7: 210 | D7: South | E7: 3.3333333 | K7: Mar | N7: 0 | P7: 0 | Q7: 0
A8: Home | B8: 1515 | D8: West | E8: 3.4285714 | K8: Apr | M8: 0 | O8: 0 | Q8: 0
A9: Toys | B9: 395 | D9: Grand Total | E9: 3.7647059 | K9: May | L9: 0 | M9: 0 | N9: 54 | O9: 0 | P9: 43 | Q9: 97
A10: East | B10: 3459 | K10: Jun | L10: 63 | M10: 1606 | N10: 0 | O10: 0 | Q10: 1669
A11: Books | B11: 350 | K11: Jul | L11: 42 | M11: 104 | N11: 0 | O11: 0 | P11: 313 | Q11: 459
A12: Electronics | B12: 365 | K12: Aug | M12: 0 | N12: 0 | P12: 0 | Q12: 0
A13: Fashion | B13: 653 | D13: Row Labels | E13: Count of Order Status | K13: Sep | L13: 0 | M13: 692 | N13: 172 | O13: 430 | Q13: 1294
A14: Home | B14: 667 | D14: Cancelled | E14: 30 | K14: Oct | L14: 0 | N14: 461 | O14: 0 | P14: 609 | Q14: 1070
A15: Toys | B15: 1424 | D15: Delivered | E15: 34 | K15: Nov | L15: 0 | M15: 3260 | N15: 480 | O15: 1070 | Q15: 4810
A16: North | B16: 8051 | D16: In Transit | E16: 36 | K16: Dec | M16: 464 | N16: 43 | O16: 1785 | P16: 475 | Q16: 2767
A17: Books | B17: 464 | D17: Grand Total | E17: 100 | K17: Grand Total | L17: 127 | M17: 6126 | N17: 1376 | O17: 4203 | P17: 1824 | Q17: 13656
A18: Electronics | B18: 5530
A19: Fashion | B19: 411
A20: Home | B20: 1154
A21: Toys | B21: 492
A22: South | B22: 7135
A23: West | B23: 7317
A24: Grand Total | B24: 30618

Sheet  Advanced Reporting
A3: Count of Delivery Status | B3: Column Labels | I3: Row Labels | J3: Sum of Effective Sales
A4: Row Labels | B4: Active | C4: Cancelled | D4: Delivered | E4: Grand Total | F4: Cancellation Rate | I4: Central | J4: 3010
A5: Central | B5: 4 | C5: 5 | D5: 5 | E5: 14 | F5: =GETPIVOTDATA("[Measures].[Count of Delivery Status]",A3,"[Range].[Region]","[Range].[Region].&[Central]","[Range].[Order Status]","[Range].[Order Status].&[Cancelled]")/GETPIVOTDATA("[Measures].[Count of Delivery Status]",A3,"[Range].[Region]","[Range].[Region].&[Central]") -> 0.35714286 | I5: East | J5: 1842
A6: East | B6: 7 | C6: 3 | D6: 8 | E6: 18 | F6: =GETPIVOTDATA("[Measures].[Count of Delivery Status]",$A$3,"[Range].[Region]","[Range].[Region].&[East]","[Range].[Order Status]","[Range].[Order Status].&[Cancelled]")/GETPIVOTDATA("[Measures].[Count of Delivery Status]",$A$3,"[Range].[Region]","[Range].[Region].&[East]") -> 0.16666667 | I6: North | J6: 4075
A7: North | B7: 7 | C7: 10 | D7: 8 | E7: 25 | F7: =GETPIVOTDATA("[Measures].[Count of Delivery Status]",$A$3,"[Range].[Region]","[Range].[Region].&[North]","[Range].[Order Status]","[Range].[Order Status].&[Cancelled]")/GETPIVOTDATA("[Measures].[Count of Delivery Status]",$A$3,"[Range].[Region]","[Range].[Region].&[North]") -> 0.4 | I7: South | J7: 1063
A8: South | B8: 10 | C8: 4 | D8: 6 | E8: 20 | F8: =GETPIVOTDATA("[Measures].[Count of Delivery Status]",$A$3,"[Range].[Region]","[Range].[Region].&[South]","[Range].[Order Status]","[Range].[Order Status].&[Cancelled]")/GETPIVOTDATA("[Measures].[Count of Delivery Status]",$A$3,"[Range].[Region]","[Range].[Region].&[South]") -> 0.2 | I8: West | J8: 3666
A9: West | B9: 8 | C9: 8 | D9: 7 | E9: 23 | F9: =GETPIVOTDATA("[Measures].[Count of Delivery Status]",$A$3,"[Range].[Region]","[Range].[Region].&[West]","[Range].[Order Status]","[Range].[Order Status].&[Cancelled]")/GETPIVOTDATA("[Measures].[Count of Delivery Status]",$A$3,"[Range].[Region]","[Range].[Region].&[West]") -> 0.34782609 | I9: Grand Total | J9: 13656
A10: Grand Total | B10: 36 | C10: 30 | D10: 34 | E10: 100 | F10: =GETPIVOTDATA("[Measures].[Count of Delivery Status]",$A$3,"[Range].[Order Status]","[Range].[Order Status].&[Cancelled]")/GETPIVOTDATA("[Measures].[Count of Delivery Status]",$A$3) -> 0.3

Sheet KPI_Dashboard

Sheet Brainstorming Reflection
A4: 1. Most Successful Product Category :-
A6: Electronics is the top-performing category in terms of revenue.
A8: This indicates that Electronics is the most successful product in the dataset and contributes the largest share of sales revenue.
A10: Overall, Electronics generated ₹6126, which is the largest share of the total effective sales of ₹13,656.
A12: 2. Region with Highest Cancellation Rate :-
A14: The North region has the highest cancellation rate.
A16: The North region has the highest cancellation rate (40%), which suggests potential issues related to delivery delays, logistics management, or customer service in that region.
A18: 3. Orders Delivered Within 2 Days :-
A20: Orders where the delivery time was 2 days or less were counted.
A22: Total Orders Delivered Within 2 Days: 11
A23: This indicates that only a limited number of orders were delivered quickly, which shows there is room to improve delivery efficiency.
A25: 4. How XLOOKUP Simplifies Cross-Sheet Analysis :-
... A55: Providing customers with real-time tracking updates can reduce cancellations caused by uncertainty about delivery times.
